[
  {
    "WeekDay": 1,
    "StartTime": "8:30",
    "Odd": 0,
    "Lesson": "Анализ и визуализация данных",
    "LessonType": "л",
    "Room": "3-407",
    "FIO": "Баенхаева Аюна Валерьевна",
    "FIOshort": "Баенхаева А.В.",
    "Error": null
  },
  {
    "WeekDay": 1,
    "StartTime": "10:15",
    "Odd": 0,
    "Lesson": "Анализ и визуализация данных",
    "LessonType": "л",
    "Room": "3-403",
    "FIO": "Баенхаева Аюна Валерьевна",
    "FIOshort": "Баенхаева А.В.",
    "Error": null
  },
  {
    "WeekDay": 1,
    "StartTime": "12:00",
    "Odd": 1,
    "Lesson": "Моделирование бизнес-процессов",
    "LessonType": "л",
    "Room": "3-706",
    "FIO": "Пешкова Ольга Вячеславовна",
    "FIOshort": "Пешкова О.В.",
    "Error": null
  },
  {
    "WeekDay": 1,
    "StartTime": "12:00",
    "Odd": 2,
    "Lesson": "Анализ и визуализация данных",
    "LessonType": "пр",
    "Room": "3-407",
    "FIO": "Баенхаева Аюна Валерьевна",
    "FIOshort": "Баенхаева А.В.",
    "Error": null
  },
  {
    "WeekDay": 2,
    "StartTime": "10:15",
    "Odd": 1,
    "Lesson": "Информационное право",
    "LessonType": "л",
    "Room": "3-403",
    "FIO": "Рубина Нина Владимировна",
    "FIOshort": "Рубина Н.В.",
    "Error": null
  },
  {
    "WeekDay": 2,
    "StartTime": "10:15",
    "Odd": 2,
    "Lesson": "Командная работа и лидерство",
    "LessonType": "л",
    "Room": "3-602",
    "FIO": "Баева Ольга Николаевна",
    "FIOshort": "Баева О.Н.",
    "Error": null
  },
  {
    "WeekDay": 2,
    "StartTime": "12:00",
    "Odd": 0,
    "Lesson": "Командная работа и лидерство",
    "LessonType": "пр",
    "Room": "3-403",
    "FIO": "Баева Ольга Николаевна",
    "FIOshort": "Баева О.Н.",
    "Error": null
  },
  {
    "WeekDay": 3,
    "StartTime": "8:30",
    "Odd": 0,
    "Lesson": "Проектирование информационных систем",
    "LessonType": "пр",
    "Room": "3-407",
    "FIO": "Братищенко Владимир Владимирович",
    "FIOshort": "Братищенко В.В.",
    "Error": null
  },
  {
    "WeekDay": 3,
    "StartTime": "10:15",
    "Odd": 0,
    "Lesson": "Проектирование информационных систем",
    "LessonType": "л",
    "Room": "3-404",
    "FIO": "Братищенко Владимир Владимирович",
    "FIOshort": "Братищенко В.В.",
    "Error": null
  },
  {
    "WeekDay": 3,
    "StartTime": "12:00",
    "Odd": 0,
    "Lesson": "Рынки ИКТ и организация продаж",
    "LessonType": "пр",
    "Room": "3-407",
    "FIO": "Архипова Зоя Валентиновна",
    "FIOshort": "Архипова З.В.",
    "Error": null
  },
  {
    "WeekDay": 4,
    "StartTime": "8:30",
    "Odd": 0,
    "Lesson": "Рынки ИКТ и организация продаж",
    "LessonType": "л",
    "Room": "2-208",
    "FIO": "Архипова Зоя Валентиновна",
    "FIOshort": "Архипова З.В.",
    "Error": null
  },
  {
    "WeekDay": 4,
    "StartTime": "10:15",
    "Odd": 0,
    "Lesson": "Моделирование бизнес-процессов",
    "LessonType": "пр",
    "Room": "3-404",
    "FIO": "Пешкова Ольга Вячеславовна",
    "FIOshort": "Пешкова О.В.",
    "Error": null
  },
  {
    "WeekDay": 4,
    "StartTime": "12:00",
    "Odd": 2,
    "Lesson": "Интернет-технологии",
    "LessonType": "пр",
    "Room": "3-404",
    "FIO": "Корж Даниил Андреевич",
    "FIOshort": "Корж Д.А.",
    "Error": null
  },
  {
    "WeekDay": 5,
    "StartTime": "8:30",
    "Odd": 0,
    "Lesson": "Интернет-технологии",
    "LessonType": "пр",
    "Room": "3-407",
    "FIO": "Корж Даниил Андреевич",
    "FIOshort": "Корж Д.А.",
    "Error": null
  },
  {
    "WeekDay": 5,
    "StartTime": "10:15",
    "Odd": 0,
    "Lesson": "Интернет-технологии",
    "LessonType": "л",
    "Room": "3-403",
    "FIO": "Корж Даниил Андреевич",
    "FIOshort": "Корж Д.А.",
    "Error": null
  },
  {
    "WeekDay": 5,
    "StartTime": "12:00",
    "Odd": 0,
    "Lesson": "Информационное право",
    "LessonType": "пр",
    "Room": "3-404",
    "FIO": "Рубина Нина Владимировна",
    "FIOshort": "Рубина Н.В.",
    "Error": null
  }
]
