[
  {
    "WeekDay": 1,
    "StartTime": "10:15",
    "Odd": 0,
    "Lesson": "Физическая культура",
    "LessonType": "пр",
    "Room": "Онлайн-23",
    "FIO": "Кишинская Татьяна Александровна",
    "FIOshort": "Кишинская Т.А.",
    "Error": null
  },
  {
    "WeekDay": 1,
    "StartTime": "15:45",
    "Odd": 0,
    "Lesson": "Заготовка древесины и других лесных ресурсов",
    "LessonType": "л",
    "Room": "Онлайн-185",
    "FIO": "Никитенко Елена Борисовна",
    "FIOshort": "Никитенко Е.Б.",
    "Error": null
  },
  {
    "WeekDay": 1,
    "StartTime": "17:30",
    "Odd": 1,
    "Lesson": "Заготовка древесины и других лесных ресурсов",
    "LessonType": "пр",
    "Room": "Онлайн-146",
    "FIO": "Никитенко Елена Борисовна",
    "FIOshort": "Никитенко Е.Б.",
    "Error": null
  },
  {
    "WeekDay": 2,
    "StartTime": "14:00",
    "Odd": 0,
    "Lesson": "Использование лесов для осуществления рекреационной деятельности",
    "LessonType": "л",
    "Room": "Онлайн-236",
    "FIO": "Тирских Лариса Анатольевна",
    "FIOshort": "Тирских Л.А.",
    "Error": null
  },
  {
    "WeekDay": 2,
    "StartTime": "15:45",
    "Odd": 0,
    "Lesson": "Использование лесов для осуществления рекреационной деятельности",
    "LessonType": "пр",
    "Room": "Онлайн-198",
    "FIO": "Тирских Лариса Анатольевна",
    "FIOshort": "Тирских Л.А.",
    "Error": null
  },
  {
    "WeekDay": 2,
    "StartTime": "17:30",
    "Odd": 0,
    "Lesson": "Контроль за состоянием и использованием лесных участков",
    "LessonType": "пр",
    "Room": "Онлайн-179",
    "FIO": "Тирских Лариса Анатольевна",
    "FIOshort": "Тирских Л.А.",
    "Error": null
  },
  {
    "WeekDay": 3,
    "StartTime": "14:00",
    "Odd": 1,
    "Lesson": "Контроль за состоянием и использованием лесных участков",
    "LessonType": "пр",
    "Room": "Онлайн-225",
    "FIO": "Тирских Лариса Анатольевна",
    "FIOshort": "Тирских Л.А.",
    "Error": null
  },
  {
    "WeekDay": 3,
    "StartTime": "14:00",
    "Odd": 2,
    "Lesson": "Контроль за состоянием и использованием лесных участков",
    "LessonType": "пр",
    "Room": "Онлайн-22",
    "FIO": "Тирских Лариса Анатольевна",
    "FIOshort": "Тирских Л.А.",
    "Error": null
  },
  {
    "WeekDay": 3,
    "StartTime": "15:45",
    "Odd": 0,
    "Lesson": "Основы философии",
    "LessonType": "л",
    "Room": "Онлайн-194",
    "FIO": "Фомина Юлия Анатольевна",
    "FIOshort": "Фомина Ю.А.",
    "Error": null
  },
  {
    "WeekDay": 3,
    "StartTime": "17:30",
    "Odd": 2,
    "Lesson": "Контроль за состоянием и использованием лесных участков",
    "LessonType": "л",
    "Room": "Онлайн-161",
    "FIO": "Тирских Лариса Анатольевна",
    "FIOshort": "Тирских Л.А.",
    "Error": null
  },
  {
    "WeekDay": 4,
    "StartTime": "14:00",
    "Odd": 2,
    "Lesson": "Правовое обеспечение профессиональной деятельности",
    "LessonType": "пр",
    "Room": "Онлайн-221",
    "FIO": "Портнова Татьяна Александровна",
    "FIOshort": "Портнова Т.А.",
    "Error": null
  },
  {
    "WeekDay": 4,
    "StartTime": "15:45",
    "Odd": 1,
    "Lesson": "Правовое обеспечение профессиональной деятельности",
    "LessonType": "пр",
    "Room": "Онлайн-194",
    "FIO": "Портнова Татьяна Александровна",
    "FIOshort": "Портнова Т.А.",
    "Error": null
  },
  {
    "WeekDay": 4,
    "StartTime": "15:45",
    "Odd": 2,
    "Lesson": "Правовое обеспечение профессиональной деятельности",
    "LessonType": "пр",
    "Room": "Онлайн-196",
    "FIO": "Портнова Татьяна Александровна",
    "FIOshort": "Портнова Т.А.",
    "Error": null
  },
  {
    "WeekDay": 4,
    "StartTime": "17:30",
    "Odd": 1,
    "Lesson": "Правовое обеспечение профессиональной деятельности",
    "LessonType": "пр",
    "Room": "Онлайн-166",
    "FIO": "Портнова Татьяна Александровна",
    "FIOshort": "Портнова Т.А.",
    "Error": null
  },
  {
    "WeekDay": 4,
    "StartTime": "17:30",
    "Odd": 2,
    "Lesson": "Контроль за состоянием и использованием лесных участков",
    "LessonType": "л",
    "Room": "Онлайн-165",
    "FIO": "Тирских Лариса Анатольевна",
    "FIOshort": "Тирских Л.А.",
    "Error": null
  },
  {
    "WeekDay": 5,
    "StartTime": "10:15",
    "Odd": 2,
    "Lesson": "Иностранный язык",
    "LessonType": "пр",
    "Room": "Онлайн-251",
    "FIO": "Латышева Валентина Александровна",
    "FIOshort": "Латышева В.А.",
    "Error": null
  },
  {
    "WeekDay": 5,
    "StartTime": "12:00",
    "Odd": 2,
    "Lesson": "Заготовка древесины и других лесных ресурсов",
    "LessonType": "л",
    "Room": "Онлайн-252",
    "FIO": "Крамынина Ирина Эдуардовна",
    "FIOshort": "Крамынина И.Э.",
    "Error": null
  },
  {
    "WeekDay": 5,
    "StartTime": "14:00",
    "Odd": 2,
    "Lesson": "Заготовка древесины и других лесных ресурсов",
    "LessonType": "пр",
    "Room": "Онлайн-226",
    "FIO": "Крамынина Ирина Эдуардовна",
    "FIOshort": "Крамынина И.Э.",
    "Error": null
  },
  {
    "WeekDay": 5,
    "StartTime": "15:45",
    "Odd": 1,
    "Lesson": "Использование лесов для осуществления рекреационной деятельности",
    "LessonType": "пр",
    "Room": "Онлайн-191",
    "FIO": "Тирских Лариса Анатольевна",
    "FIOshort": "Тирских Л.А.",
    "Error": null
  },
  {
    "WeekDay": 5,
    "StartTime": "17:30",
    "Odd": 1,
    "Lesson": "Контроль за состоянием и использованием лесных участков",
    "LessonType": "пр",
    "Room": "Онлайн-156",
    "FIO": "Тирских Лариса Анатольевна",
    "FIOshort": "Тирских Л.А.",
    "Error": null
  },
  {
    "WeekDay": 6,
    "StartTime": "10:15",
    "Odd": 2,
    "Lesson": "Иностранный язык",
    "LessonType": "пр",
    "Room": "Онлайн-218",
    "FIO": "Латышева Валентина Александровна",
    "FIOshort": "Латышева В.А.",
    "Error": null
  },
  {
    "WeekDay": 6,
    "StartTime": "12:00",
    "Odd": 0,
    "Lesson": "Использование лесов для осуществления рекреационной деятельности",
    "LessonType": "л",
    "Room": "Онлайн-206",
    "FIO": "Тирских Лариса Анатольевна",
    "FIOshort": "Тирских Л.А.",
    "Error": null
  },
  {
    "WeekDay": 6,
    "StartTime": "14:00",
    "Odd": 1,
    "Lesson": "Заготовка древесины и других лесных ресурсов",
    "LessonType": "л",
    "Room": "Онлайн-174",
    "FIO": "Крамынина Ирина Эдуардовна",
    "FIOshort": "Крамынина И.Э.",
    "Error": null
  },
  {
    "WeekDay": 6,
    "StartTime": "14:00",
    "Odd": 2,
    "Lesson": "Контроль за состоянием и использованием лесных участков",
    "LessonType": "пр",
    "Room": "Онлайн-159",
    "FIO": "Тирских Лариса Анатольевна",
    "FIOshort": "Тирских Л.А.",
    "Error": null
  },
  {
    "WeekDay": 6,
    "StartTime": "15:45",
    "Odd": 1,
    "Lesson": "Заготовка древесины и других лесных ресурсов",
    "LessonType": "пр",
    "Room": "Онлайн-147",
    "FIO": "Крамынина Ирина Эдуардовна",
    "FIOshort": "Крамынина И.Э.",
    "Error": null
  },
  {
    "WeekDay": 6,
    "StartTime": "15:45",
    "Odd": 2,
    "Lesson": "Использование лесов для осуществления рекреационной деятельности",
    "LessonType": "пр",
    "Room": "Онлайн-143",
    "FIO": "Тирских Лариса Анатольевна",
    "FIOshort": "Тирских Л.А.",
    "Error": null
  }
]
