[
  {
    "WeekDay": 1,
    "StartTime": "17:30",
    "Odd": 0,
    "Lesson": "Проблемы противодействия коррупции в системе органов государственной власти Российской Федерации и субъектов Российской Федерации",
    "LessonType": "пр",
    "Room": "Онлайн-17",
    "FIO": "Эвертовская Лариса Владимировна",
    "FIOshort": "Эвертовская Л.В.",
    "Error": null
  },
  {
    "WeekDay": 1,
    "StartTime": "19:15",
    "Odd": 0,
    "Lesson": "Правовое регулирование государственной и муниципальной службы в Российской Федерации",
    "LessonType": "пр",
    "Room": "Онлайн-14",
    "FIO": "Эвертовская Лариса Владимировна",
    "FIOshort": "Эвертовская Л.В.",
    "Error": null
  },
  {
    "WeekDay": 2,
    "StartTime": "17:30",
    "Odd": 0,
    "Lesson": "Проблемы правового регулирования административного процесса в Российской Федерации",
    "LessonType": "пр",
    "Room": "Онлайн-4",
    "FIO": "Кирьянова Ольга Викторовна",
    "FIOshort": "Кирьянова О.В.",
    "Error": null
  },
  {
    "WeekDay": 2,
    "StartTime": "19:15",
    "Odd": 2,
    "Lesson": "Проблемы правового регулирования административного процесса в Российской Федерации",
    "LessonType": "л",
    "Room": "Онлайн-4",
    "FIO": "Кирьянова Ольга Викторовна",
    "FIOshort": "Кирьянова О.В.",
    "Error": null
  },
  {
    "WeekDay": 3,
    "StartTime": "17:30",
    "Odd": 0,
    "Lesson": "Конституционно-правовая ответственность",
    "LessonType": "пр",
    "Room": "Онлайн-20",
    "FIO": "Суркова Ирина Сергеевна",
    "FIOshort": "Суркова И.С.",
    "Error": null
  },
  {
    "WeekDay": 5,
    "StartTime": "17:30",
    "Odd": 0,
    "Lesson": "Административная ответственность в Российской Федерации: проблемы теории и практики",
    "LessonType": "пр",
    "Room": "Онлайн-8",
    "FIO": "Эвертовская Лариса Владимировна",
    "FIOshort": "Эвертовская Л.В.",
    "Error": null
  },
  {
    "WeekDay": 5,
    "StartTime": "19:15",
    "Odd": 1,
    "Lesson": "Административная ответственность в Российской Федерации: проблемы теории и практики",
    "LessonType": "л",
    "Room": "6-312",
    "FIO": "Эвертовская Лариса Владимировна",
    "FIOshort": "Эвертовская Л.В.",
    "Error": null
  },
  {
    "WeekDay": 6,
    "StartTime": "12:00",
    "Odd": 0,
    "Lesson": "Контроль и надзор в сфере государственного управления",
    "LessonType": "пр",
    "Room": "Онлайн-13",
    "FIO": "Таскаев Николай Николаевич",
    "FIOshort": "Таскаев Н.Н.",
    "Error": null
  }
]
