[
  {
    "WeekDay": 1,
    "StartTime": "12:00",
    "Odd": 1,
    "Lesson": "Информационные технологии",
    "LessonType": "пр",
    "Room": "2-405",
    "FIO": "Баенхаева Аюна Валерьевна",
    "FIOshort": "Баенхаева А.В.",
    "Error": null
  },
  {
    "WeekDay": 1,
    "StartTime": "14:00",
    "Odd": 0,
    "Lesson": "Иностранный язык для делового общения",
    "LessonType": "пр",
    "Room": "1-417",
    "FIO": "Китова Елена Борисовна",
    "FIOshort": "Китова Е.Б.",
    "Error": null
  },
  {
    "WeekDay": 1,
    "StartTime": "14:00",
    "Odd": 0,
    "Lesson": "Иностранный язык для делового общения",
    "LessonType": "пр",
    "Room": "1-307",
    "FIO": "Сметанина Татьяна Витальевна",
    "FIOshort": "Сметанина Т.В.",
    "Error": null
  },
  {
    "WeekDay": 1,
    "StartTime": "14:00",
    "Odd": 0,
    "Lesson": "Иностранный язык для делового общения",
    "LessonType": "пр",
    "Room": "1-311",
    "FIO": "Бимакова Руфина Рашидовна",
    "FIOshort": "Бимакова Р.Р.",
    "Error": null
  },
  {
    "WeekDay": 1,
    "StartTime": "15:45",
    "Odd": 0,
    "Lesson": "Иностранный язык в профессиональной сфере",
    "LessonType": "пр",
    "Room": "1-416",
    "FIO": "Китова Елена Борисовна",
    "FIOshort": "Китова Е.Б.",
    "Error": null
  },
  {
    "WeekDay": 1,
    "StartTime": "15:45",
    "Odd": 0,
    "Lesson": "Иностранный язык в профессиональной сфере",
    "LessonType": "пр",
    "Room": "1-307",
    "FIO": "Сметанина Татьяна Витальевна",
    "FIOshort": "Сметанина Т.В.",
    "Error": null
  },
  {
    "WeekDay": 1,
    "StartTime": "15:45",
    "Odd": 0,
    "Lesson": "Иностранный язык в профессиональной сфере",
    "LessonType": "пр",
    "Room": "1-414",
    "FIO": "Бимакова Руфина Рашидовна",
    "FIOshort": "Бимакова Р.Р.",
    "Error": null
  },
  {
    "WeekDay": 1,
    "StartTime": "17:30",
    "Odd": 1,
    "Lesson": "Экономическая культура",
    "LessonType": "л",
    "Room": "2-308",
    "FIO": "Юшков Олег Александрович",
    "FIOshort": "Юшков О.А.",
    "Error": null
  },
  {
    "WeekDay": 1,
    "StartTime": "17:30",
    "Odd": 2,
    "Lesson": "Математические и инструментальные средства в экономике",
    "LessonType": "л",
    "Room": "2-416",
    "FIO": "Аксенюшкина Елена Владимировна",
    "FIOshort": "Аксенюшкина Е.В.",
    "Error": null
  },
  {
    "WeekDay": 2,
    "StartTime": "10:15",
    "Odd": 0,
    "Lesson": "Экономика организации",
    "LessonType": "пр",
    "Room": "2-312",
    "FIO": "Самаруха Алексей Викторович",
    "FIOshort": "Самаруха А.В.",
    "Error": null
  },
  {
    "WeekDay": 2,
    "StartTime": "12:00",
    "Odd": 0,
    "Lesson": "Микроэкономика",
    "LessonType": "пр",
    "Room": "2-415",
    "FIO": "Шавкунова Ирина Сергеевна",
    "FIOshort": "Шавкунова И.С.",
    "Error": null
  },
  {
    "WeekDay": 2,
    "StartTime": "14:00",
    "Odd": 0,
    "Lesson": "Математические и инструментальные средства в экономике",
    "LessonType": "л",
    "Room": "3-706",
    "FIO": "Аксенюшкина Елена Владимировна",
    "FIOshort": "Аксенюшкина Е.В.",
    "Error": null
  },
  {
    "WeekDay": 2,
    "StartTime": "15:45",
    "Odd": 0,
    "Lesson": "Математические и инструментальные средства в экономике",
    "LessonType": "пр",
    "Room": "3-703",
    "FIO": "Аксенюшкина Елена Владимировна",
    "FIOshort": "Аксенюшкина Е.В.",
    "Error": null
  },
  {
    "WeekDay": 3,
    "StartTime": "12:00",
    "Odd": 0,
    "Lesson": "Математические и инструментальные средства в экономике",
    "LessonType": "пр",
    "Room": "3-705",
    "FIO": "Аксенюшкина Елена Владимировна",
    "FIOshort": "Аксенюшкина Е.В.",
    "Error": null
  },
  {
    "WeekDay": 3,
    "StartTime": "14:00",
    "Odd": 0,
    "Lesson": "Иностранный язык для делового общения",
    "LessonType": "пр",
    "Room": "1-416",
    "FIO": "Китова Елена Борисовна",
    "FIOshort": "Китова Е.Б.",
    "Error": null
  },
  {
    "WeekDay": 3,
    "StartTime": "14:00",
    "Odd": 0,
    "Lesson": "Иностранный язык для делового общения",
    "LessonType": "пр",
    "Room": "1-409",
    "FIO": "Сметанина Татьяна Витальевна",
    "FIOshort": "Сметанина Т.В.",
    "Error": null
  },
  {
    "WeekDay": 3,
    "StartTime": "14:00",
    "Odd": 0,
    "Lesson": "Иностранный язык для делового общения",
    "LessonType": "пр",
    "Room": "1-415",
    "FIO": "Бимакова Руфина Рашидовна",
    "FIOshort": "Бимакова Р.Р.",
    "Error": null
  },
  {
    "WeekDay": 3,
    "StartTime": "15:45",
    "Odd": 0,
    "Lesson": "Микроэкономика",
    "LessonType": "л",
    "Room": "2-416",
    "FIO": "Шавкунова Ирина Сергеевна",
    "FIOshort": "Шавкунова И.С.",
    "Error": null
  },
  {
    "WeekDay": 3,
    "StartTime": "17:30",
    "Odd": 0,
    "Lesson": "История России",
    "LessonType": "л",
    "Room": "2-308",
    "FIO": "Казарин Виктор Николаевич",
    "FIOshort": "Казарин В.Н.",
    "Error": null
  },
  {
    "WeekDay": 4,
    "StartTime": "14:00",
    "Odd": 1,
    "Lesson": "Управление личной эффективностью",
    "LessonType": "л",
    "Room": "4-212",
    "FIO": "Арбатская Елена Анатольевна",
    "FIOshort": "Арбатская Е.А.",
    "Error": null
  },
  {
    "WeekDay": 4,
    "StartTime": "14:00",
    "Odd": 2,
    "Lesson": "Финансовая грамотность",
    "LessonType": "л",
    "Room": "4-212",
    "FIO": "Файберг Татьяна Владимировна",
    "FIOshort": "Файберг Т.В.",
    "Error": null
  },
  {
    "WeekDay": 4,
    "StartTime": "15:45",
    "Odd": 1,
    "Lesson": "Экономика организации",
    "LessonType": "л",
    "Room": "4-203",
    "FIO": "Самаруха Алексей Викторович",
    "FIOshort": "Самаруха А.В.",
    "Error": null
  },
  {
    "WeekDay": 4,
    "StartTime": "15:45",
    "Odd": 2,
    "Lesson": "Финансовая грамотность",
    "LessonType": "пр",
    "Room": "2-208",
    "FIO": "Ковтун Лира Раисовна",
    "FIOshort": "Ковтун Л.Р.",
    "Error": null
  },
  {
    "WeekDay": 4,
    "StartTime": "17:30",
    "Odd": 0,
    "Lesson": "Информационные технологии",
    "LessonType": "пр",
    "Room": "3-407",
    "FIO": "Баенхаева Аюна Валерьевна",
    "FIOshort": "Баенхаева А.В.",
    "Error": null
  },
  {
    "WeekDay": 5,
    "StartTime": "12:00",
    "Odd": 0,
    "Lesson": "История России",
    "LessonType": "пр",
    "Room": "1-201",
    "FIO": "Кузьмин Юрий Васильевич",
    "FIOshort": "Кузьмин Ю.В.",
    "Error": null
  },
  {
    "WeekDay": 5,
    "StartTime": "14:00",
    "Odd": 0,
    "Lesson": "Иностранный язык для делового общения",
    "LessonType": "пр",
    "Room": "1-409",
    "FIO": "Китова Елена Борисовна",
    "FIOshort": "Китова Е.Б.",
    "Error": null
  },
  {
    "WeekDay": 5,
    "StartTime": "14:00",
    "Odd": 0,
    "Lesson": "Иностранный язык для делового общения",
    "LessonType": "пр",
    "Room": "1-307",
    "FIO": "Сметанина Татьяна Витальевна",
    "FIOshort": "Сметанина Т.В.",
    "Error": null
  },
  {
    "WeekDay": 5,
    "StartTime": "14:00",
    "Odd": 0,
    "Lesson": "Иностранный язык для делового общения",
    "LessonType": "пр",
    "Room": "1-416",
    "FIO": "Бимакова Руфина Рашидовна",
    "FIOshort": "Бимакова Р.Р.",
    "Error": null
  },
  {
    "WeekDay": 5,
    "StartTime": "15:45",
    "Odd": 1,
    "Lesson": "Экономическая культура",
    "LessonType": "пр",
    "Room": "1-201",
    "FIO": "Юшков Олег Александрович",
    "FIOshort": "Юшков О.А.",
    "Error": null
  },
  {
    "WeekDay": 5,
    "StartTime": "15:45",
    "Odd": 2,
    "Lesson": "Управление личной эффективностью",
    "LessonType": "пр",
    "Room": "1-201",
    "FIO": "Арбатская Елена Анатольевна",
    "FIOshort": "Арбатская Е.А.",
    "Error": null
  },
  {
    "WeekDay": 6,
    "StartTime": "8:30",
    "Odd": 0,
    "Lesson": "Физическая культура",
    "LessonType": "пр",
    "Room": "11-103",
    "FIO": "Изотова Инга Игоревна",
    "FIOshort": "Изотова И.И.",
    "Error": null
  }
]
