[
  {
    "WeekDay": 1,
    "StartTime": "8:30",
    "Odd": 0,
    "Lesson": "Складская логистика",
    "LessonType": "л",
    "Room": "3-704",
    "FIO": "Силантьев Александр Валерьевич",
    "FIOshort": "Силантьев А.В.",
    "Error": null
  },
  {
    "WeekDay": 1,
    "StartTime": "10:15",
    "Odd": 0,
    "Lesson": "Складская логистика",
    "LessonType": "пр",
    "Room": "3-704",
    "FIO": "Силантьев Александр Валерьевич",
    "FIOshort": "Силантьев А.В.",
    "Error": null
  },
  {
    "WeekDay": 2,
    "StartTime": "8:30",
    "Odd": 0,
    "Lesson": "Управление продажами",
    "LessonType": "л",
    "Room": "3-602",
    "FIO": "Демиденко Сергей Владимирович",
    "FIOshort": "Демиденко С.В.",
    "Error": null
  },
  {
    "WeekDay": 2,
    "StartTime": "10:15",
    "Odd": 0,
    "Lesson": "Управление продажами",
    "LessonType": "пр",
    "Room": "3-602",
    "FIO": "Демиденко Сергей Владимирович",
    "FIOshort": "Демиденко С.В.",
    "Error": null
  },
  {
    "WeekDay": 3,
    "StartTime": "8:30",
    "Odd": 1,
    "Lesson": "Закупки в муниципальных и государственных организациях",
    "LessonType": "пр",
    "Room": "3-603",
    "FIO": "Антипина Полина Витальевна",
    "FIOshort": "Антипина П.В.",
    "Error": null
  },
  {
    "WeekDay": 3,
    "StartTime": "8:30",
    "Odd": 2,
    "Lesson": "Закупки в муниципальных и государственных организациях",
    "LessonType": "л",
    "Room": "3-603",
    "FIO": "Антипина Полина Витальевна",
    "FIOshort": "Антипина П.В.",
    "Error": null
  },
  {
    "WeekDay": 3,
    "StartTime": "10:15",
    "Odd": 0,
    "Lesson": "Управление конфликтами и ведение переговоров",
    "LessonType": "пр",
    "Room": "3-603",
    "FIO": "Демиденко Сергей Владимирович",
    "FIOshort": "Демиденко С.В.",
    "Error": null
  },
  {
    "WeekDay": 3,
    "StartTime": "10:15",
    "Odd": 0,
    "Lesson": "Управление конфликтами и ведение переговоров",
    "LessonType": "пр",
    "Room": "3-603",
    "FIO": "Баева Ольга Николаевна",
    "FIOshort": "Баева О.Н.",
    "Error": null
  },
  {
    "WeekDay": 3,
    "StartTime": "10:15",
    "Odd": 0,
    "Lesson": "Управление конфликтами и ведение переговоров",
    "LessonType": "пр",
    "Room": "3-603",
    "FIO": "Григорьев Андрей Владимирович",
    "FIOshort": "Григорьев А.В.",
    "Error": null
  },
  {
    "WeekDay": 3,
    "StartTime": "12:00",
    "Odd": 1,
    "Lesson": "Управление конфликтами и ведение переговоров",
    "LessonType": "л",
    "Room": "3-602",
    "FIO": "Баева Ольга Николаевна",
    "FIOshort": "Баева О.Н.",
    "Error": null
  },
  {
    "WeekDay": 3,
    "StartTime": "12:00",
    "Odd": 2,
    "Lesson": "Мерчендайзинг",
    "LessonType": "л",
    "Room": "3-603",
    "FIO": "Рыженков Алексей Геннадьевич",
    "FIOshort": "Рыженков А.Г.",
    "Error": null
  },
  {
    "WeekDay": 4,
    "StartTime": "8:30",
    "Odd": 0,
    "Lesson": "Мерчендайзинг",
    "LessonType": "пр",
    "Room": "3-704",
    "FIO": "Рыженков Алексей Геннадьевич",
    "FIOshort": "Рыженков А.Г.",
    "Error": null
  },
  {
    "WeekDay": 4,
    "StartTime": "10:15",
    "Odd": 0,
    "Lesson": "Стратегический менеджмент",
    "LessonType": "л",
    "Room": "3-704",
    "FIO": "Сараева Оксана Николаевна",
    "FIOshort": "Сараева О.Н.",
    "Error": null
  },
  {
    "WeekDay": 4,
    "StartTime": "12:00",
    "Odd": 0,
    "Lesson": "Стратегический менеджмент",
    "LessonType": "пр",
    "Room": "3-704",
    "FIO": "Сараева Оксана Николаевна",
    "FIOshort": "Сараева О.Н.",
    "Error": null
  },
  {
    "WeekDay": 4,
    "StartTime": "12:00",
    "Odd": 0,
    "Lesson": "Стратегический менеджмент",
    "LessonType": "пр",
    "Room": "3-704",
    "FIO": "Исупов Илья Владимирович",
    "FIOshort": "Исупов И.В.",
    "Error": null
  },
  {
    "WeekDay": 5,
    "StartTime": "8:30",
    "Odd": 0,
    "Lesson": "Бизнес-планирование и организация предпринимательской деятельности",
    "LessonType": "л",
    "Room": "3-704",
    "FIO": "Сараева Оксана Николаевна",
    "FIOshort": "Сараева О.Н.",
    "Error": null
  },
  {
    "WeekDay": 5,
    "StartTime": "10:15",
    "Odd": 0,
    "Lesson": "Бизнес-планирование и организация предпринимательской деятельности",
    "LessonType": "пр",
    "Room": "3-704",
    "FIO": "Сараева Оксана Николаевна",
    "FIOshort": "Сараева О.Н.",
    "Error": null
  },
  {
    "WeekDay": 5,
    "StartTime": "12:00",
    "Odd": 1,
    "Lesson": "Налогообложение и кредитование торгово-закупочной деятельности",
    "LessonType": "пр",
    "Room": "3-903",
    "FIO": "Холмовский Станислав Геннадьевич",
    "FIOshort": "Холмовский С.Г.",
    "Error": null
  },
  {
    "WeekDay": 5,
    "StartTime": "12:00",
    "Odd": 2,
    "Lesson": "Налогообложение и кредитование торгово-закупочной деятельности",
    "LessonType": "л",
    "Room": "3-903",
    "FIO": "Холмовский Станислав Геннадьевич",
    "FIOshort": "Холмовский С.Г.",
    "Error": null
  }
]
