[
  {
    "WeekDay": 1,
    "StartTime": "8:30",
    "Odd": 1,
    "Lesson": "Гражданская позиция",
    "LessonType": "пр",
    "Room": "2-408",
    "FIO": "Лянной Глеб Геннадьевич",
    "FIOshort": "Лянной Г.Г.",
    "Error": null
  },
  {
    "WeekDay": 1,
    "StartTime": "8:30",
    "Odd": 2,
    "Lesson": "Гражданская позиция",
    "LessonType": "л",
    "Room": "2-408",
    "FIO": "Лянной Глеб Геннадьевич",
    "FIOshort": "Лянной Г.Г.",
    "Error": null
  },
  {
    "WeekDay": 1,
    "StartTime": "10:15",
    "Odd": 1,
    "Lesson": "Гражданская позиция",
    "LessonType": "пр",
    "Room": "2-408",
    "FIO": "Лянной Глеб Геннадьевич",
    "FIOshort": "Лянной Г.Г.",
    "Error": null
  },
  {
    "WeekDay": 1,
    "StartTime": "10:15",
    "Odd": 2,
    "Lesson": "Гражданская позиция",
    "LessonType": "л",
    "Room": "2-408",
    "FIO": "Лянной Глеб Геннадьевич",
    "FIOshort": "Лянной Г.Г.",
    "Error": null
  },
  {
    "WeekDay": 1,
    "StartTime": "12:00",
    "Odd": 1,
    "Lesson": "Финансовая грамотность",
    "LessonType": "пр",
    "Room": "2-408",
    "FIO": "Кузнецова Надежда Васильевна",
    "FIOshort": "Кузнецова Н.В.",
    "Error": null
  },
  {
    "WeekDay": 1,
    "StartTime": "12:00",
    "Odd": 2,
    "Lesson": "Финансовая грамотность",
    "LessonType": "л",
    "Room": "2-408",
    "FIO": "Кузнецова Надежда Васильевна",
    "FIOshort": "Кузнецова Н.В.",
    "Error": null
  },
  {
    "WeekDay": 2,
    "StartTime": "8:30",
    "Odd": 1,
    "Lesson": "Организация социальной работы с пожилыми",
    "LessonType": "пр",
    "Room": "2-112",
    "FIO": "Лобова Елена Анатольевна",
    "FIOshort": "Лобова Е.А.",
    "Error": null
  },
  {
    "WeekDay": 2,
    "StartTime": "8:30",
    "Odd": 1,
    "Lesson": "Организация социальной работы с пожилыми",
    "LessonType": "пр",
    "Room": "2-112",
    "FIO": "Тарабан Ольга Вячеславовна",
    "FIOshort": "Тарабан О.В.",
    "Error": null
  },
  {
    "WeekDay": 2,
    "StartTime": "8:30",
    "Odd": 2,
    "Lesson": "Основы деятельности некоммерческих организаций",
    "LessonType": "л",
    "Room": "2-112",
    "FIO": "Артамонова Виктория Владимировна",
    "FIOshort": "Артамонова В.В.",
    "Error": null
  },
  {
    "WeekDay": 2,
    "StartTime": "10:15",
    "Odd": 1,
    "Lesson": "Организация социальной работы с пожилыми",
    "LessonType": "пр",
    "Room": "2-112",
    "FIO": "Лобова Елена Анатольевна",
    "FIOshort": "Лобова Е.А.",
    "Error": null
  },
  {
    "WeekDay": 2,
    "StartTime": "10:15",
    "Odd": 1,
    "Lesson": "Организация социальной работы с пожилыми",
    "LessonType": "пр",
    "Room": "2-112",
    "FIO": "Тарабан Ольга Вячеславовна",
    "FIOshort": "Тарабан О.В.",
    "Error": null
  },
  {
    "WeekDay": 2,
    "StartTime": "10:15",
    "Odd": 2,
    "Lesson": "Организация социальной работы с пожилыми",
    "LessonType": "л",
    "Room": "2-112",
    "FIO": "Тарабан Ольга Вячеславовна",
    "FIOshort": "Тарабан О.В.",
    "Error": null
  },
  {
    "WeekDay": 2,
    "StartTime": "12:00",
    "Odd": 1,
    "Lesson": "Социальное обеспечение",
    "LessonType": "пр",
    "Room": "2-112",
    "FIO": "Соломеин Алексей Александрович",
    "FIOshort": "Соломеин А.А.",
    "Error": null
  },
  {
    "WeekDay": 2,
    "StartTime": "12:00",
    "Odd": 1,
    "Lesson": "Социальное обеспечение",
    "LessonType": "пр",
    "Room": "2-112",
    "FIO": "Крутоверцева Екатерина Павловна",
    "FIOshort": "Крутоверцева Е.П.",
    "Error": null
  },
  {
    "WeekDay": 2,
    "StartTime": "12:00",
    "Odd": 2,
    "Lesson": "Опыт организации социальной работы за рубежом",
    "LessonType": "л",
    "Room": "2-112",
    "FIO": "Тарабан Ольга Вячеславовна",
    "FIOshort": "Тарабан О.В.",
    "Error": null
  },
  {
    "WeekDay": 3,
    "StartTime": "8:30",
    "Odd": 1,
    "Lesson": "Социальные проекты и программы",
    "LessonType": "пр",
    "Room": "2-315",
    "FIO": "Седых Ольга Геннадьевна",
    "FIOshort": "Седых О.Г.",
    "Error": null
  },
  {
    "WeekDay": 3,
    "StartTime": "8:30",
    "Odd": 1,
    "Lesson": "Социальные проекты и программы",
    "LessonType": "пр",
    "Room": "2-315",
    "FIO": "Соболев Александр Владимирович",
    "FIOshort": "Соболев А.В.",
    "Error": null
  },
  {
    "WeekDay": 3,
    "StartTime": "8:30",
    "Odd": 2,
    "Lesson": "Опыт организации социальной работы за рубежом",
    "LessonType": "пр",
    "Room": "2-315",
    "FIO": "Тарабан Ольга Вячеславовна",
    "FIOshort": "Тарабан О.В.",
    "Error": null
  },
  {
    "WeekDay": 3,
    "StartTime": "10:15",
    "Odd": 1,
    "Lesson": "Социальные проекты и программы",
    "LessonType": "пр",
    "Room": "2-315",
    "FIO": "Седых Ольга Геннадьевна",
    "FIOshort": "Седых О.Г.",
    "Error": null
  },
  {
    "WeekDay": 3,
    "StartTime": "10:15",
    "Odd": 1,
    "Lesson": "Социальные проекты и программы",
    "LessonType": "пр",
    "Room": "2-315",
    "FIO": "Соболев Александр Владимирович",
    "FIOshort": "Соболев А.В.",
    "Error": null
  },
  {
    "WeekDay": 3,
    "StartTime": "10:15",
    "Odd": 2,
    "Lesson": "Опыт организации социальной работы за рубежом",
    "LessonType": "пр",
    "Room": "2-315",
    "FIO": "Тарабан Ольга Вячеславовна",
    "FIOshort": "Тарабан О.В.",
    "Error": null
  },
  {
    "WeekDay": 3,
    "StartTime": "12:00",
    "Odd": 1,
    "Lesson": "Социальные проекты и программы",
    "LessonType": "пр",
    "Room": "2-315",
    "FIO": "Седых Ольга Геннадьевна",
    "FIOshort": "Седых О.Г.",
    "Error": null
  },
  {
    "WeekDay": 3,
    "StartTime": "12:00",
    "Odd": 1,
    "Lesson": "Социальные проекты и программы",
    "LessonType": "пр",
    "Room": "2-315",
    "FIO": "Соболев Александр Владимирович",
    "FIOshort": "Соболев А.В.",
    "Error": null
  },
  {
    "WeekDay": 3,
    "StartTime": "12:00",
    "Odd": 2,
    "Lesson": "Социальное обеспечение",
    "LessonType": "пр",
    "Room": "2-310",
    "FIO": "Крутоверцева Екатерина Павловна",
    "FIOshort": "Крутоверцева Е.П.",
    "Error": null
  },
  {
    "WeekDay": 3,
    "StartTime": "12:00",
    "Odd": 2,
    "Lesson": "Социальное обеспечение",
    "LessonType": "пр",
    "Room": "2-310",
    "FIO": "Соломеин Алексей Александрович",
    "FIOshort": "Соломеин А.А.",
    "Error": null
  },
  {
    "WeekDay": 4,
    "StartTime": "8:30",
    "Odd": 1,
    "Lesson": "Основы деятельности некоммерческих организаций",
    "LessonType": "пр",
    "Room": "2-314",
    "FIO": "Артамонова Виктория Владимировна",
    "FIOshort": "Артамонова В.В.",
    "Error": null
  },
  {
    "WeekDay": 4,
    "StartTime": "8:30",
    "Odd": 1,
    "Lesson": "Основы деятельности некоммерческих организаций",
    "LessonType": "пр",
    "Room": "2-314",
    "FIO": "Соболев Александр Владимирович",
    "FIOshort": "Соболев А.В.",
    "Error": null
  },
  {
    "WeekDay": 4,
    "StartTime": "8:30",
    "Odd": 2,
    "Lesson": "Организация социальной работы с инвалидами",
    "LessonType": "пр",
    "Room": "2-314",
    "FIO": "Копалкина Евгения Геннадьевна",
    "FIOshort": "Копалкина Е.Г.",
    "Error": null
  },
  {
    "WeekDay": 4,
    "StartTime": "10:15",
    "Odd": 1,
    "Lesson": "Основы деятельности некоммерческих организаций",
    "LessonType": "пр",
    "Room": "2-314",
    "FIO": "Артамонова Виктория Владимировна",
    "FIOshort": "Артамонова В.В.",
    "Error": null
  },
  {
    "WeekDay": 4,
    "StartTime": "10:15",
    "Odd": 1,
    "Lesson": "Основы деятельности некоммерческих организаций",
    "LessonType": "пр",
    "Room": "2-314",
    "FIO": "Соболев Александр Владимирович",
    "FIOshort": "Соболев А.В.",
    "Error": null
  },
  {
    "WeekDay": 4,
    "StartTime": "10:15",
    "Odd": 2,
    "Lesson": "Организация социальной работы с инвалидами",
    "LessonType": "пр",
    "Room": "2-314",
    "FIO": "Копалкина Евгения Геннадьевна",
    "FIOshort": "Копалкина Е.Г.",
    "Error": null
  },
  {
    "WeekDay": 4,
    "StartTime": "12:00",
    "Odd": 0,
    "Lesson": "Статистика отраслей социальной сферы",
    "LessonType": "пр",
    "Room": "2-314",
    "FIO": "Малютина Светлана Анатольевна",
    "FIOshort": "Малютина С.А.",
    "Error": null
  },
  {
    "WeekDay": 5,
    "StartTime": "8:30",
    "Odd": 1,
    "Lesson": "Организация социальной работы с инвалидами",
    "LessonType": "л",
    "Room": "2-314",
    "FIO": "Копалкина Евгения Геннадьевна",
    "FIOshort": "Копалкина Е.Г.",
    "Error": null
  },
  {
    "WeekDay": 5,
    "StartTime": "10:15",
    "Odd": 0,
    "Lesson": "Социальные проекты и программы",
    "LessonType": "л",
    "Room": "2-314",
    "FIO": "Седых Ольга Геннадьевна",
    "FIOshort": "Седых О.Г.",
    "Error": null
  },
  {
    "WeekDay": 5,
    "StartTime": "12:00",
    "Odd": 0,
    "Lesson": "Статистика отраслей социальной сферы",
    "LessonType": "л",
    "Room": "2-314",
    "FIO": "Малютина Светлана Анатольевна",
    "FIOshort": "Малютина С.А.",
    "Error": null
  },
  {
    "WeekDay": 5,
    "StartTime": "14:00",
    "Odd": 2,
    "Lesson": "Социальное обеспечение",
    "LessonType": "л",
    "Room": "3-706",
    "FIO": "Крутоверцева Екатерина Павловна",
    "FIOshort": "Крутоверцева Е.П.",
    "Error": null
  }
]
