[
  {
    "WeekDay": 1,
    "StartTime": "10:15",
    "Odd": 0,
    "Lesson": "Техническое оснащение предприятий общественного питания",
    "LessonType": "л",
    "Room": "Онлайн-233",
    "FIO": "Горячкина Ирина Сергеевна",
    "FIOshort": "Горячкина И.С.",
    "Error": null
  },
  {
    "WeekDay": 1,
    "StartTime": "12:00",
    "Odd": 0,
    "Lesson": "Микробиология, санитария и гигиена в пищевом производстве",
    "LessonType": "л",
    "Room": "Онлайн-230",
    "FIO": "Горячкина Ирина Сергеевна",
    "FIOshort": "Горячкина И.С.",
    "Error": null
  },
  {
    "WeekDay": 1,
    "StartTime": "14:00",
    "Odd": 0,
    "Lesson": "Микробиология, санитария и гигиена в пищевом производстве",
    "LessonType": "пр",
    "Room": "Онлайн-201",
    "FIO": "Горячкина Ирина Сергеевна",
    "FIOshort": "Горячкина И.С.",
    "Error": null
  },
  {
    "WeekDay": 1,
    "StartTime": "15:45",
    "Odd": 0,
    "Lesson": "Техническое оснащение предприятий общественного питания",
    "LessonType": "пр",
    "Room": "Онлайн-170",
    "FIO": "Горячкина Ирина Сергеевна",
    "FIOshort": "Горячкина И.С.",
    "Error": null
  },
  {
    "WeekDay": 2,
    "StartTime": "10:15",
    "Odd": 0,
    "Lesson": "Техническое оснащение предприятий общественного питания",
    "LessonType": "пр",
    "Room": "Онлайн-236",
    "FIO": "Горячкина Ирина Сергеевна",
    "FIOshort": "Горячкина И.С.",
    "Error": null
  },
  {
    "WeekDay": 2,
    "StartTime": "12:00",
    "Odd": 0,
    "Lesson": "Математика",
    "LessonType": "л",
    "Room": "Онлайн-245",
    "FIO": "Лапаева Татьяна Николаевна",
    "FIOshort": "Лапаева Т.Н.",
    "Error": null
  },
  {
    "WeekDay": 2,
    "StartTime": "14:00",
    "Odd": 0,
    "Lesson": "Химия",
    "LessonType": "л",
    "Room": "Онлайн-219",
    "FIO": "Черника Елена Яковлевна",
    "FIOshort": "Черника Е.Я.",
    "Error": null
  },
  {
    "WeekDay": 2,
    "StartTime": "17:30",
    "Odd": 0,
    "Lesson": "Физическая культура",
    "LessonType": "пр",
    "Room": "Онлайн-116",
    "FIO": "Тигунцев Сергей Александрович",
    "FIOshort": "Тигунцев С.А.",
    "Error": null
  },
  {
    "WeekDay": 3,
    "StartTime": "8:30",
    "Odd": 2,
    "Lesson": "Метрология и стандартизация",
    "LessonType": "пр",
    "Room": "Онлайн-19",
    "FIO": "Степанченко Арина Владимировна",
    "FIOshort": "Степанченко А.В.",
    "Error": null
  },
  {
    "WeekDay": 3,
    "StartTime": "10:15",
    "Odd": 0,
    "Lesson": "Иностранный язык",
    "LessonType": "пр",
    "Room": "Онлайн-227",
    "FIO": "Кольцова Алла Викторовна",
    "FIOshort": "Кольцова А.В.",
    "Error": null
  },
  {
    "WeekDay": 3,
    "StartTime": "12:00",
    "Odd": 0,
    "Lesson": "Выполнение работ по профессии \"Повар\"",
    "LessonType": "л",
    "Room": "Онлайн-230",
    "FIO": "Горячкина Ирина Сергеевна",
    "FIOshort": "Горячкина И.С.",
    "Error": null
  },
  {
    "WeekDay": 4,
    "StartTime": "10:15",
    "Odd": 0,
    "Lesson": "Математика",
    "LessonType": "л",
    "Room": "Онлайн-226",
    "FIO": "Лапаева Татьяна Николаевна",
    "FIOshort": "Лапаева Т.Н.",
    "Error": null
  },
  {
    "WeekDay": 4,
    "StartTime": "12:00",
    "Odd": 0,
    "Lesson": "Метрология и стандартизация",
    "LessonType": "л",
    "Room": "Онлайн-225",
    "FIO": "Степанченко Арина Владимировна",
    "FIOshort": "Степанченко А.В.",
    "Error": null
  },
  {
    "WeekDay": 4,
    "StartTime": "14:00",
    "Odd": 0,
    "Lesson": "Выполнение работ по профессии \"Повар\"",
    "LessonType": "пр",
    "Room": "Онлайн-215",
    "FIO": "Горячкина Ирина Сергеевна",
    "FIOshort": "Горячкина И.С.",
    "Error": null
  },
  {
    "WeekDay": 4,
    "StartTime": "15:45",
    "Odd": 1,
    "Lesson": "Химия",
    "LessonType": "л",
    "Room": "Онлайн-177",
    "FIO": "Черника Елена Яковлевна",
    "FIOshort": "Черника Е.Я.",
    "Error": null
  },
  {
    "WeekDay": 4,
    "StartTime": "15:45",
    "Odd": 2,
    "Lesson": "Выполнение работ по профессии \"Повар\"",
    "LessonType": "пр",
    "Room": "Онлайн-176",
    "FIO": "Горячкина Ирина Сергеевна",
    "FIOshort": "Горячкина И.С.",
    "Error": null
  },
  {
    "WeekDay": 5,
    "StartTime": "8:30",
    "Odd": 1,
    "Lesson": "Химия",
    "LessonType": "пр",
    "Room": "Онлайн-203",
    "FIO": "Черника Елена Яковлевна",
    "FIOshort": "Черника Е.Я.",
    "Error": null
  },
  {
    "WeekDay": 5,
    "StartTime": "10:15",
    "Odd": 1,
    "Lesson": "Выполнение работ по профессии \"Повар\"",
    "LessonType": "л",
    "Room": "Онлайн-241",
    "FIO": "Горячкина Ирина Сергеевна",
    "FIOshort": "Горячкина И.С.",
    "Error": null
  },
  {
    "WeekDay": 5,
    "StartTime": "10:15",
    "Odd": 2,
    "Lesson": "Техническое оснащение предприятий общественного питания",
    "LessonType": "л",
    "Room": "Онлайн-232",
    "FIO": "Горячкина Ирина Сергеевна",
    "FIOshort": "Горячкина И.С.",
    "Error": null
  },
  {
    "WeekDay": 5,
    "StartTime": "12:00",
    "Odd": 0,
    "Lesson": "Техническое оснащение предприятий общественного питания",
    "LessonType": "л",
    "Room": "Онлайн-242",
    "FIO": "Горячкина Ирина Сергеевна",
    "FIOshort": "Горячкина И.С.",
    "Error": null
  },
  {
    "WeekDay": 5,
    "StartTime": "14:00",
    "Odd": 0,
    "Lesson": "Математика",
    "LessonType": "пр",
    "Room": "Онлайн-207",
    "FIO": "Лапаева Татьяна Николаевна",
    "FIOshort": "Лапаева Т.Н.",
    "Error": null
  }
]
