[
  {
    "WeekDay": 1,
    "StartTime": "10:15",
    "Odd": 1,
    "Lesson": "История",
    "LessonType": "л",
    "Room": "11-414",
    "FIO": "Третьяков Денис Геннадьевич",
    "FIOshort": "Третьяков Д.Г.",
    "Error": null
  },
  {
    "WeekDay": 1,
    "StartTime": "10:15",
    "Odd": 2,
    "Lesson": "История",
    "LessonType": "пр",
    "Room": "11-414",
    "FIO": "Третьяков Денис Геннадьевич",
    "FIOshort": "Третьяков Д.Г.",
    "Error": null
  },
  {
    "WeekDay": 1,
    "StartTime": "12:00",
    "Odd": 0,
    "Lesson": "Финансы, денежное обращение и кредит",
    "LessonType": "л",
    "Room": "11-408",
    "FIO": "Колонович Елена Григорьевна",
    "FIOshort": "Колонович Е.Г.",
    "Error": null
  },
  {
    "WeekDay": 1,
    "StartTime": "14:00",
    "Odd": 0,
    "Lesson": "Организация и технология торговли",
    "LessonType": "л",
    "Room": "11-408",
    "FIO": "Алексеева Любовь Алексеевна",
    "FIOshort": "Алексеева Л.А.",
    "Error": null
  },
  {
    "WeekDay": 2,
    "StartTime": "8:30",
    "Odd": 0,
    "Lesson": "Физическая культура",
    "LessonType": "пр",
    "Room": "11-113",
    "FIO": "Чмаркова Елена Гирадьевна",
    "FIOshort": "Чмаркова Е.Г.",
    "Error": null
  },
  {
    "WeekDay": 2,
    "StartTime": "10:15",
    "Odd": 0,
    "Lesson": "Практические основы бухгалтерского учета финансовых активов",
    "LessonType": "л",
    "Room": "11-308",
    "FIO": "Саяпина Алина Николаевна",
    "FIOshort": "Саяпина А.Н.",
    "Error": null
  },
  {
    "WeekDay": 2,
    "StartTime": "12:00",
    "Odd": 1,
    "Lesson": "Практические основы бухгалтерского учета финансовых активов",
    "LessonType": "л",
    "Room": "11-401",
    "FIO": "Саяпина Алина Николаевна",
    "FIOshort": "Саяпина А.Н.",
    "Error": null
  },
  {
    "WeekDay": 2,
    "StartTime": "12:00",
    "Odd": 2,
    "Lesson": "Менеджмент",
    "LessonType": "л",
    "Room": "11-401",
    "FIO": "Козлова Елена Владимировна",
    "FIOshort": "Козлова Е.В.",
    "Error": null
  },
  {
    "WeekDay": 3,
    "StartTime": "12:00",
    "Odd": 0,
    "Lesson": "Правовое обеспечение профессиональной деятельности",
    "LessonType": "л",
    "Room": "11-401",
    "FIO": "Секлетин Роман Викторович",
    "FIOshort": "Секлетин Р.В.",
    "Error": null
  },
  {
    "WeekDay": 3,
    "StartTime": "14:00",
    "Odd": 0,
    "Lesson": "Иностранный язык в профессиональной деятельности",
    "LessonType": "пр",
    "Room": "11-301",
    "FIO": "Фаркова Ирина Анатольевна",
    "FIOshort": "Фаркова И.А.",
    "Error": null
  },
  {
    "WeekDay": 4,
    "StartTime": "8:30",
    "Odd": 0,
    "Lesson": "Статистика",
    "LessonType": "л",
    "Room": "11-309",
    "FIO": "Кузнецова Елена Владимировна",
    "FIOshort": "Кузнецова Е.В.",
    "Error": null
  },
  {
    "WeekDay": 4,
    "StartTime": "10:15",
    "Odd": 1,
    "Lesson": "Менеджмент",
    "LessonType": "л",
    "Room": "11-308",
    "FIO": "Козлова Елена Владимировна",
    "FIOshort": "Козлова Е.В.",
    "Error": null
  },
  {
    "WeekDay": 4,
    "StartTime": "10:15",
    "Odd": 2,
    "Lesson": "Менеджмент",
    "LessonType": "пр",
    "Room": "11-308",
    "FIO": "Козлова Елена Владимировна",
    "FIOshort": "Козлова Е.В.",
    "Error": null
  },
  {
    "WeekDay": 4,
    "StartTime": "12:00",
    "Odd": 1,
    "Lesson": "Выполнение работ по профессии \"Кассир\"",
    "LessonType": "пр",
    "Room": "11-301",
    "FIO": "Садиева Виктория Викторовна",
    "FIOshort": "Садиева В.В.",
    "Error": null
  },
  {
    "WeekDay": 4,
    "StartTime": "12:00",
    "Odd": 2,
    "Lesson": "Выполнение работ по профессии \"Кассир\"",
    "LessonType": "л",
    "Room": "11-301",
    "FIO": "Садиева Виктория Викторовна",
    "FIOshort": "Садиева В.В.",
    "Error": null
  },
  {
    "WeekDay": 5,
    "StartTime": "8:30",
    "Odd": 2,
    "Lesson": "Правовое обеспечение профессиональной деятельности",
    "LessonType": "пр",
    "Room": "11-306",
    "FIO": "Секлетин Роман Викторович",
    "FIOshort": "Секлетин Р.В.",
    "Error": null
  },
  {
    "WeekDay": 5,
    "StartTime": "10:15",
    "Odd": 0,
    "Lesson": "Финансы, денежное обращение и кредит",
    "LessonType": "пр",
    "Room": "11-306",
    "FIO": "Колонович Елена Григорьевна",
    "FIOshort": "Колонович Е.Г.",
    "Error": null
  },
  {
    "WeekDay": 5,
    "StartTime": "12:00",
    "Odd": 0,
    "Lesson": "Организация и технология торговли",
    "LessonType": "пр",
    "Room": "11-412",
    "FIO": "Алексеева Любовь Алексеевна",
    "FIOshort": "Алексеева Л.А.",
    "Error": null
  }
]
