[
  {
    "WeekDay": 1,
    "StartTime": "8:30",
    "Odd": 0,
    "Lesson": "История и география стран второго иностранного языка",
    "LessonType": "л",
    "Room": "1-201",
    "FIO": "Лапыренок Роман Викторович",
    "FIOshort": "Лапыренок Р.В.",
    "Error": null
  },
  {
    "WeekDay": 1,
    "StartTime": "10:15",
    "Odd": 1,
    "Lesson": "Профессионально-ориентированный письменный практикум (первый иностранный язык)",
    "LessonType": "пр",
    "Room": "1-201",
    "FIO": "Курная Мария Юрьевна",
    "FIOshort": "Курная М.Ю.",
    "Error": null
  },
  {
    "WeekDay": 1,
    "StartTime": "10:15",
    "Odd": 2,
    "Lesson": "История и география стран второго иностранного языка",
    "LessonType": "пр",
    "Room": "1-201",
    "FIO": "Лапыренок Роман Викторович",
    "FIOshort": "Лапыренок Р.В.",
    "Error": null
  },
  {
    "WeekDay": 1,
    "StartTime": "14:00",
    "Odd": 0,
    "Lesson": "Физическая культура и спорт (элективные дисциплины)",
    "LessonType": "пр",
    "Room": "11-103",
    "FIO": "Малеванный Андрей Александрович",
    "FIOshort": "Малеванный А.А.",
    "Error": null
  },
  {
    "WeekDay": 2,
    "StartTime": "8:30",
    "Odd": 1,
    "Lesson": "Основы теории второго иностранного языка",
    "LessonType": "л",
    "Room": "1-420",
    "FIO": "Шереметьева Анна Алексеевна",
    "FIOshort": "Шереметьева А.А.",
    "Error": null
  },
  {
    "WeekDay": 2,
    "StartTime": "8:30",
    "Odd": 1,
    "Lesson": "Основы теории второго иностранного языка",
    "LessonType": "л",
    "Room": "1-203",
    "FIO": "Зыкова Валентина Анатольевна",
    "FIOshort": "Зыкова В.А.",
    "Error": null
  },
  {
    "WeekDay": 2,
    "StartTime": "8:30",
    "Odd": 2,
    "Lesson": "Основы теории второго иностранного языка",
    "LessonType": "пр",
    "Room": "1-420",
    "FIO": "Шереметьева Анна Алексеевна",
    "FIOshort": "Шереметьева А.А.",
    "Error": null
  },
  {
    "WeekDay": 2,
    "StartTime": "8:30",
    "Odd": 2,
    "Lesson": "Основы теории второго иностранного языка",
    "LessonType": "пр",
    "Room": "1-203",
    "FIO": "Зыкова Валентина Анатольевна",
    "FIOshort": "Зыкова В.А.",
    "Error": null
  },
  {
    "WeekDay": 2,
    "StartTime": "10:15",
    "Odd": 0,
    "Lesson": "Практикум по культуре речевого общения (второй иностранный язык)",
    "LessonType": "пр",
    "Room": "1-420",
    "FIO": "Шереметьева Анна Алексеевна",
    "FIOshort": "Шереметьева А.А.",
    "Error": null
  },
  {
    "WeekDay": 2,
    "StartTime": "10:15",
    "Odd": 0,
    "Lesson": "Практикум по культуре речевого общения (второй иностранный язык)",
    "LessonType": "пр",
    "Room": "1-203",
    "FIO": "Зыкова Валентина Анатольевна",
    "FIOshort": "Зыкова В.А.",
    "Error": null
  },
  {
    "WeekDay": 3,
    "StartTime": "8:30",
    "Odd": 0,
    "Lesson": "Профессионально-ориентированный письменный практикум (первый иностранный язык)",
    "LessonType": "пр",
    "Room": "1-203",
    "FIO": "Курная Мария Юрьевна",
    "FIOshort": "Курная М.Ю.",
    "Error": null
  },
  {
    "WeekDay": 3,
    "StartTime": "10:15",
    "Odd": 1,
    "Lesson": "Функциональные стили письма (первый иностранный язык)",
    "LessonType": "пр",
    "Room": "1-203",
    "FIO": "Рыбалко Светлана Александровна",
    "FIOshort": "Рыбалко С.А.",
    "Error": null
  },
  {
    "WeekDay": 3,
    "StartTime": "10:15",
    "Odd": 2,
    "Lesson": "Функциональные стили письма (первый иностранный язык)",
    "LessonType": "л",
    "Room": "1-203",
    "FIO": "Рыбалко Светлана Александровна",
    "FIOshort": "Рыбалко С.А.",
    "Error": null
  },
  {
    "WeekDay": 3,
    "StartTime": "12:00",
    "Odd": 0,
    "Lesson": "Практикум по культуре речевого общения (первый иностранный язык)",
    "LessonType": "пр",
    "Room": "1-402",
    "FIO": "Егорова Марина Алексеевна",
    "FIOshort": "Егорова М.А.",
    "Error": null
  },
  {
    "WeekDay": 4,
    "StartTime": "8:30",
    "Odd": 0,
    "Lesson": "Практикум по культуре речевого общения (первый иностранный язык)",
    "LessonType": "пр",
    "Room": "1-417",
    "FIO": "Егорова Марина Алексеевна",
    "FIOshort": "Егорова М.А.",
    "Error": null
  },
  {
    "WeekDay": 4,
    "StartTime": "10:15",
    "Odd": 0,
    "Lesson": "Практикум по культуре речевого общения (второй иностранный язык)",
    "LessonType": "пр",
    "Room": "1-307",
    "FIO": "Шереметьева Анна Алексеевна",
    "FIOshort": "Шереметьева А.А.",
    "Error": null
  },
  {
    "WeekDay": 4,
    "StartTime": "10:15",
    "Odd": 0,
    "Lesson": "Практикум по культуре речевого общения (второй иностранный язык)",
    "LessonType": "пр",
    "Room": "1-203",
    "FIO": "Зыкова Валентина Анатольевна",
    "FIOshort": "Зыкова В.А.",
    "Error": null
  },
  {
    "WeekDay": 4,
    "StartTime": "12:00",
    "Odd": 1,
    "Lesson": "Когнитивные основы грамматики (первый иностранный язык)",
    "LessonType": "пр",
    "Room": "1-405",
    "FIO": "Универсалюк Елена Александровна",
    "FIOshort": "Универсалюк Е.А.",
    "Error": null
  },
  {
    "WeekDay": 4,
    "StartTime": "12:00",
    "Odd": 2,
    "Lesson": "Когнитивные основы грамматики (первый иностранный язык)",
    "LessonType": "л",
    "Room": "1-405",
    "FIO": "Универсалюк Елена Александровна",
    "FIOshort": "Универсалюк Е.А.",
    "Error": null
  },
  {
    "WeekDay": 4,
    "StartTime": "14:00",
    "Odd": 0,
    "Lesson": "Физическая культура и спорт (элективные дисциплины)",
    "LessonType": "пр",
    "Room": "11-103",
    "FIO": "Малеванный Андрей Александрович",
    "FIOshort": "Малеванный А.А.",
    "Error": null
  },
  {
    "WeekDay": 5,
    "StartTime": "8:30",
    "Odd": 0,
    "Lesson": "Практикум по культуре речевого общения (первый иностранный язык)",
    "LessonType": "пр",
    "Room": "1-410",
    "FIO": "Сметанина-Крушевски Наталья Викторовна",
    "FIOshort": "Сметанина-Крушевски ",
    "Error": null
  },
  {
    "WeekDay": 5,
    "StartTime": "10:15",
    "Odd": 0,
    "Lesson": "Практикум по культуре речевого общения (первый иностранный язык)",
    "LessonType": "пр",
    "Room": "1-410",
    "FIO": "Сметанина-Крушевски Наталья Викторовна",
    "FIOshort": "Сметанина-Крушевски ",
    "Error": null
  }
]