[
  {
    "WeekDay": 1,
    "StartTime": "10:15",
    "Odd": 0,
    "Lesson": "Теория и практика перевода (второй иностранный язык)",
    "LessonType": "пр",
    "Room": "10-205",
    "FIO": "Бреева Анна Павловна",
    "FIOshort": "Бреева А.П.",
    "Error": null
  },
  {
    "WeekDay": 1,
    "StartTime": "12:00",
    "Odd": 0,
    "Lesson": "Практикум по культуре речевого общения (первый иностранный язык)",
    "LessonType": "пр",
    "Room": "10-201(б)",
    "FIO": "Скобёлкина Наталья Михайловна",
    "FIOshort": "Скобёлкина Н.М.",
    "Error": null
  },
  {
    "WeekDay": 1,
    "StartTime": "12:00",
    "Odd": 0,
    "Lesson": "Трудные вопросы грамматики русского языка",
    "LessonType": "пр",
    "Room": "10-102",
    "FIO": "Терских Татьяна Филипповна",
    "FIOshort": "Терских Т.Ф.",
    "Error": null
  },
  {
    "WeekDay": 1,
    "StartTime": "14:00",
    "Odd": 0,
    "Lesson": "Практикум по культуре речевого общения (первый иностранный язык)",
    "LessonType": "пр",
    "Room": "10-201(б)",
    "FIO": "Скобёлкина Наталья Михайловна",
    "FIOshort": "Скобёлкина Н.М.",
    "Error": null
  },
  {
    "WeekDay": 2,
    "StartTime": "8:30",
    "Odd": 1,
    "Lesson": "Русская фразеология",
    "LessonType": "л",
    "Room": "10-103",
    "FIO": "Непомнящих Екатерина Александровна",
    "FIOshort": "Непомнящих Е.А.",
    "Error": null
  },
  {
    "WeekDay": 2,
    "StartTime": "8:30",
    "Odd": 2,
    "Lesson": "Основы теории межкультурной коммуникации",
    "LessonType": "л",
    "Room": "10-205",
    "FIO": "Вагенлетнер Марина Сергеевна",
    "FIOshort": "Вагенлетнер М.С.",
    "Error": null
  },
  {
    "WeekDay": 2,
    "StartTime": "10:15",
    "Odd": 0,
    "Lesson": "Основы теории межкультурной коммуникации",
    "LessonType": "пр",
    "Room": "10-205",
    "FIO": "Вагенлетнер Марина Сергеевна",
    "FIOshort": "Вагенлетнер М.С.",
    "Error": null
  },
  {
    "WeekDay": 2,
    "StartTime": "10:15",
    "Odd": 0,
    "Lesson": "Русская фразеология",
    "LessonType": "пр",
    "Room": "10-102",
    "FIO": "Непомнящих Екатерина Александровна",
    "FIOshort": "Непомнящих Е.А.",
    "Error": null
  },
  {
    "WeekDay": 2,
    "StartTime": "12:00",
    "Odd": 0,
    "Lesson": "Аудио-визуальный курс русского языка",
    "LessonType": "пр",
    "Room": "10-201(в)",
    "FIO": "Третьякова Евгения Валерьевна",
    "FIOshort": "Третьякова Е.В.",
    "Error": null
  },
  {
    "WeekDay": 2,
    "StartTime": "12:00",
    "Odd": 0,
    "Lesson": "Русский язык в деловой сфере общения",
    "LessonType": "пр",
    "Room": "10-305",
    "FIO": "Курьянова Светлана Александровна",
    "FIOshort": "Курьянова С.А.",
    "Error": null
  },
  {
    "WeekDay": 2,
    "StartTime": "14:00",
    "Odd": 0,
    "Lesson": "Русский язык в деловой сфере общения",
    "LessonType": "пр",
    "Room": "10-305",
    "FIO": "Курьянова Светлана Александровна",
    "FIOshort": "Курьянова С.А.",
    "Error": null
  },
  {
    "WeekDay": 2,
    "StartTime": "14:00",
    "Odd": 0,
    "Lesson": "Русский язык в СМИ",
    "LessonType": "пр",
    "Room": "10-201(в)",
    "FIO": "Кичатинова Ольга Владимировна",
    "FIOshort": "Кичатинова О.В.",
    "Error": null
  },
  {
    "WeekDay": 3,
    "StartTime": "8:30",
    "Odd": 0,
    "Lesson": "Русская фразеология",
    "LessonType": "пр",
    "Room": "10-102",
    "FIO": "Непомнящих Екатерина Александровна",
    "FIOshort": "Непомнящих Е.А.",
    "Error": null
  },
  {
    "WeekDay": 3,
    "StartTime": "10:15",
    "Odd": 0,
    "Lesson": "Основы теории межкультурной коммуникации",
    "LessonType": "пр",
    "Room": "10-204",
    "FIO": "Вагенлетнер Марина Сергеевна",
    "FIOshort": "Вагенлетнер М.С.",
    "Error": null
  },
  {
    "WeekDay": 3,
    "StartTime": "10:15",
    "Odd": 0,
    "Lesson": "Теория и практика перевода (первый иностранный язык)",
    "LessonType": "пр",
    "Room": "10-201(в)",
    "FIO": "Зарбуева Анастасия Ильинична",
    "FIOshort": "Зарбуева А.И.",
    "Error": null
  },
  {
    "WeekDay": 3,
    "StartTime": "12:00",
    "Odd": 0,
    "Lesson": "Русский язык (продвинутый курс)",
    "LessonType": "пр",
    "Room": "10-201(б)",
    "FIO": "Муран Ольга Владимировна",
    "FIOshort": "Муран О.В.",
    "Error": null
  },
  {
    "WeekDay": 3,
    "StartTime": "12:00",
    "Odd": 0,
    "Lesson": "Теория и практика перевода (первый иностранный язык)",
    "LessonType": "пр",
    "Room": "10-201(в)",
    "FIO": "Зарбуева Анастасия Ильинична",
    "FIOshort": "Зарбуева А.И.",
    "Error": null
  },
  {
    "WeekDay": 3,
    "StartTime": "14:00",
    "Odd": 2,
    "Lesson": "Русский язык (продвинутый курс)",
    "LessonType": "пр",
    "Room": "10-201(в)",
    "FIO": "Муран Ольга Владимировна",
    "FIOshort": "Муран О.В.",
    "Error": null
  },
  {
    "WeekDay": 4,
    "StartTime": "10:15",
    "Odd": 0,
    "Lesson": "Аудио-визуальный курс русского языка",
    "LessonType": "пр",
    "Room": "10-201(а)",
    "FIO": "Терских Татьяна Филипповна",
    "FIOshort": "Терских Т.Ф.",
    "Error": null
  },
  {
    "WeekDay": 4,
    "StartTime": "10:15",
    "Odd": 0,
    "Lesson": "Русский язык в СМИ",
    "LessonType": "пр",
    "Room": "10-201(в)",
    "FIO": "Кичатинова Ольга Владимировна",
    "FIOshort": "Кичатинова О.В.",
    "Error": null
  },
  {
    "WeekDay": 4,
    "StartTime": "12:00",
    "Odd": 1,
    "Lesson": "Русский язык (продвинутый курс)",
    "LessonType": "пр",
    "Room": "10-302",
    "FIO": "Муран Ольга Владимировна",
    "FIOshort": "Муран О.В.",
    "Error": null
  },
  {
    "WeekDay": 4,
    "StartTime": "12:00",
    "Odd": 1,
    "Lesson": "Практикум по культуре речевого общения (первый иностранный язык)",
    "LessonType": "пр",
    "Room": "10-201(б)",
    "FIO": "Скобёлкина Наталья Михайловна",
    "FIOshort": "Скобёлкина Н.М.",
    "Error": null
  },
  {
    "WeekDay": 4,
    "StartTime": "12:00",
    "Odd": 2,
    "Lesson": "Практикум по культуре речевого общения (первый иностранный язык)",
    "LessonType": "пр",
    "Room": "10-201(в)",
    "FIO": "Скобёлкина Наталья Михайловна",
    "FIOshort": "Скобёлкина Н.М.",
    "Error": null
  },
  {
    "WeekDay": 4,
    "StartTime": "12:00",
    "Odd": 2,
    "Lesson": "Трудные вопросы грамматики русского языка",
    "LessonType": "пр",
    "Room": "10-302",
    "FIO": "Терских Татьяна Филипповна",
    "FIOshort": "Терских Т.Ф.",
    "Error": null
  },
  {
    "WeekDay": 5,
    "StartTime": "12:00",
    "Odd": 0,
    "Lesson": "Философия",
    "LessonType": "пр",
    "Room": "2-208",
    "FIO": "Немцева Анна Владимировна",
    "FIOshort": "Немцева А.В.",
    "Error": null
  },
  {
    "WeekDay": 5,
    "StartTime": "14:00",
    "Odd": 0,
    "Lesson": "Философия",
    "LessonType": "л",
    "Room": "2-208",
    "FIO": "Немцева Анна Владимировна",
    "FIOshort": "Немцева А.В.",
    "Error": null
  },
  {
    "WeekDay": 5,
    "StartTime": "15:45",
    "Odd": 2,
    "Lesson": "Трудные вопросы грамматики русского языка",
    "LessonType": "пр",
    "Room": "10-104",
    "FIO": "Терских Татьяна Филипповна",
    "FIOshort": "Терских Т.Ф.",
    "Error": null
  }
]
