[
  {
    "WeekDay": 1,
    "StartTime": "14:00",
    "Odd": 0,
    "Lesson": "Методология научного познания",
    "LessonType": "л",
    "Room": "2-411",
    "FIO": "Прохоренкова Светлана Александровна",
    "FIOshort": "Прохоренкова С.А.",
    "Error": null
  },
  {
    "WeekDay": 1,
    "StartTime": "15:45",
    "Odd": 0,
    "Lesson": "Методология научного познания",
    "LessonType": "пр",
    "Room": "2-217",
    "FIO": "Прохоренкова Светлана Александровна",
    "FIOshort": "Прохоренкова С.А.",
    "Error": null
  },
  {
    "WeekDay": 1,
    "StartTime": "17:30",
    "Odd": 0,
    "Lesson": "Теория классической литературы (динамические искусства)",
    "LessonType": "л",
    "Room": "2-314",
    "FIO": "Прохоренкова Светлана Александровна",
    "FIOshort": "Прохоренкова С.А.",
    "Error": null
  },
  {
    "WeekDay": 3,
    "StartTime": "10:15",
    "Odd": 0,
    "Lesson": "Иностранный язык (профессиональный)",
    "LessonType": "пр",
    "Room": "1-309",
    "FIO": "Доржиева Долгорма Цырендашиевна",
    "FIOshort": "Доржиева Д.Ц.",
    "Error": null
  },
  {
    "WeekDay": 3,
    "StartTime": "12:00",
    "Odd": 0,
    "Lesson": "Иностранный язык (профессиональный)",
    "LessonType": "пр",
    "Room": "2-317",
    "FIO": "Доржиева Долгорма Цырендашиевна",
    "FIOshort": "Доржиева Д.Ц.",
    "Error": null
  },
  {
    "WeekDay": 3,
    "StartTime": "14:00",
    "Odd": 0,
    "Lesson": "Немецкий язык (профессиональный)",
    "LessonType": "пр",
    "Room": "1-414",
    "FIO": "Паульзен Наталья Сергеевна",
    "FIOshort": "Паульзен Н.С.",
    "Error": null
  },
  {
    "WeekDay": 3,
    "StartTime": "15:45",
    "Odd": 0,
    "Lesson": "Немецкий язык (профессиональный)",
    "LessonType": "пр",
    "Room": "1-414",
    "FIO": "Паульзен Наталья Сергеевна",
    "FIOshort": "Паульзен Н.С.",
    "Error": null
  },
  {
    "WeekDay": 4,
    "StartTime": "8:30",
    "Odd": 1,
    "Lesson": "Теория классической литературы (динамические искусства)",
    "LessonType": "пр",
    "Room": "4-203",
    "FIO": "Прохоренкова Светлана Александровна",
    "FIOshort": "Прохоренкова С.А.",
    "Error": null
  },
  {
    "WeekDay": 4,
    "StartTime": "10:15",
    "Odd": 0,
    "Lesson": "Институциональная экономика",
    "LessonType": "л",
    "Room": "4-203",
    "FIO": "Рудяков Василий Анатольевич",
    "FIOshort": "Рудяков В.А.",
    "Error": null
  },
  {
    "WeekDay": 4,
    "StartTime": "12:00",
    "Odd": 0,
    "Lesson": "Институциональная экономика",
    "LessonType": "пр",
    "Room": "4-203",
    "FIO": "Рудяков Василий Анатольевич",
    "FIOshort": "Рудяков В.А.",
    "Error": null
  },
  {
    "WeekDay": 5,
    "StartTime": "14:00",
    "Odd": 0,
    "Lesson": "Эстетические концепции в системе культуры",
    "LessonType": "л",
    "Room": "2-317",
    "FIO": "Прохоренкова Светлана Александровна",
    "FIOshort": "Прохоренкова С.А.",
    "Error": null
  },
  {
    "WeekDay": 5,
    "StartTime": "15:45",
    "Odd": 0,
    "Lesson": "Эстетические концепции в системе культуры",
    "LessonType": "пр",
    "Room": "2-317",
    "FIO": "Прохоренкова Светлана Александровна",
    "FIOshort": "Прохоренкова С.А.",
    "Error": null
  },
  {
    "WeekDay": 5,
    "StartTime": "17:30",
    "Odd": 0,
    "Lesson": "Теория классической литературы (динамические искусства)",
    "LessonType": "пр",
    "Room": "2-317",
    "FIO": "Прохоренкова Светлана Александровна",
    "FIOshort": "Прохоренкова С.А.",
    "Error": null
  },
  {
    "WeekDay": 6,
    "StartTime": "8:30",
    "Odd": 2,
    "Lesson": "Библиотековедение",
    "LessonType": "л",
    "Room": "2-317",
    "FIO": "Серебрякова Светлана Викторовна",
    "FIOshort": "Серебрякова С.В.",
    "Error": null
  },
  {
    "WeekDay": 6,
    "StartTime": "10:15",
    "Odd": 2,
    "Lesson": "Библиотековедение",
    "LessonType": "пр",
    "Room": "2-317",
    "FIO": "Серебрякова Светлана Викторовна",
    "FIOshort": "Серебрякова С.В.",
    "Error": null
  },
  {
    "WeekDay": 6,
    "StartTime": "12:00",
    "Odd": 2,
    "Lesson": "Библиотековедение",
    "LessonType": "пр",
    "Room": "2-317",
    "FIO": "Серебрякова Светлана Викторовна",
    "FIOshort": "Серебрякова С.В.",
    "Error": null
  }
]
