[
  {
    "WeekDay": 1,
    "StartTime": "8:30",
    "Odd": 0,
    "Lesson": "Основы философии",
    "LessonType": "л",
    "Room": "11-210",
    "FIO": "Тараканов Павел Николаевич",
    "FIOshort": "Тараканов П.Н.",
    "Error": null
  },
  {
    "WeekDay": 1,
    "StartTime": "8:30",
    "Odd": 0,
    "Lesson": "Основы философии",
    "LessonType": "л",
    "Room": "11-210",
    "FIO": "Тараканов Павел Николаевич",
    "FIOshort": "Тараканов П.Н.",
    "Error": null
  },
  {
    "WeekDay": 1,
    "StartTime": "8:30",
    "Odd": 0,
    "Lesson": "Основы философии",
    "LessonType": "л",
    "Room": "11-210",
    "FIO": "Тараканов Павел Николаевич",
    "FIOshort": "Тараканов П.Н.",
    "Error": null
  },
  {
    "WeekDay": 1,
    "StartTime": "8:30",
    "Odd": 0,
    "Lesson": "Основы философии",
    "LessonType": "л",
    "Room": "11-210",
    "FIO": "Тараканов Павел Николаевич",
    "FIOshort": "Тараканов П.Н.",
    "Error": null
  },
  {
    "WeekDay": 1,
    "StartTime": "10:15",
    "Odd": 0,
    "Lesson": "Использование лесов для осуществления рекреационной деятельности",
    "LessonType": "л",
    "Room": "11-112",
    "FIO": "Пуничева Екатерина Леонидовна",
    "FIOshort": "Пуничева Е.Л.",
    "Error": null
  },
  {
    "WeekDay": 1,
    "StartTime": "10:15",
    "Odd": 0,
    "Lesson": "Использование лесов для осуществления рекреационной деятельности",
    "LessonType": "л",
    "Room": "11-112",
    "FIO": "Пуничева Екатерина Леонидовна",
    "FIOshort": "Пуничева Е.Л.",
    "Error": null
  },
  {
    "WeekDay": 1,
    "StartTime": "12:00",
    "Odd": 1,
    "Lesson": "Основы философии",
    "LessonType": "пр",
    "Room": "11-415",
    "FIO": "Тараканов Павел Николаевич",
    "FIOshort": "Тараканов П.Н.",
    "Error": null
  },
  {
    "WeekDay": 1,
    "StartTime": "12:00",
    "Odd": 1,
    "Lesson": "Основы философии",
    "LessonType": "пр",
    "Room": "11-415",
    "FIO": "Тараканов Павел Николаевич",
    "FIOshort": "Тараканов П.Н.",
    "Error": null
  },
  {
    "WeekDay": 2,
    "StartTime": "14:00",
    "Odd": 1,
    "Lesson": "Правовое обеспечение профессиональной деятельности",
    "LessonType": "л",
    "Room": "11-308",
    "FIO": "Портнова Татьяна Александровна",
    "FIOshort": "Портнова Т.А.",
    "Error": null
  },
  {
    "WeekDay": 2,
    "StartTime": "14:00",
    "Odd": 1,
    "Lesson": "Правовое обеспечение профессиональной деятельности",
    "LessonType": "л",
    "Room": "11-308",
    "FIO": "Портнова Татьяна Александровна",
    "FIOshort": "Портнова Т.А.",
    "Error": null
  },
  {
    "WeekDay": 2,
    "StartTime": "14:00",
    "Odd": 2,
    "Lesson": "Правовое обеспечение профессиональной деятельности",
    "LessonType": "л",
    "Room": "11-415",
    "FIO": "Портнова Татьяна Александровна",
    "FIOshort": "Портнова Т.А.",
    "Error": null
  },
  {
    "WeekDay": 2,
    "StartTime": "14:00",
    "Odd": 2,
    "Lesson": "Правовое обеспечение профессиональной деятельности",
    "LessonType": "пр",
    "Room": "11-415",
    "FIO": "Портнова Татьяна Александровна",
    "FIOshort": "Портнова Т.А.",
    "Error": null
  },
  {
    "WeekDay": 2,
    "StartTime": "15:45",
    "Odd": 0,
    "Lesson": "Правовое обеспечение профессиональной деятельности",
    "LessonType": "пр",
    "Room": "11-403",
    "FIO": "Портнова Татьяна Александровна",
    "FIOshort": "Портнова Т.А.",
    "Error": null
  },
  {
    "WeekDay": 2,
    "StartTime": "15:45",
    "Odd": 0,
    "Lesson": "Правовое обеспечение профессиональной деятельности",
    "LessonType": "пр",
    "Room": "11-403",
    "FIO": "Портнова Татьяна Александровна",
    "FIOshort": "Портнова Т.А.",
    "Error": null
  },
  {
    "WeekDay": 2,
    "StartTime": "17:30",
    "Odd": 1,
    "Lesson": "Правовое обеспечение профессиональной деятельности",
    "LessonType": "л",
    "Room": "11-112",
    "FIO": "Портнова Татьяна Александровна",
    "FIOshort": "Портнова Т.А.",
    "Error": null
  },
  {
    "WeekDay": 2,
    "StartTime": "17:30",
    "Odd": 1,
    "Lesson": "Правовое обеспечение профессиональной деятельности",
    "LessonType": "л",
    "Room": "11-112",
    "FIO": "Портнова Татьяна Александровна",
    "FIOshort": "Портнова Т.А.",
    "Error": null
  },
  {
    "WeekDay": 2,
    "StartTime": "17:30",
    "Odd": 2,
    "Lesson": "Использование лесов для осуществления рекреационной деятельности",
    "LessonType": "л",
    "Room": "11-310",
    "FIO": "Пуничева Екатерина Леонидовна",
    "FIOshort": "Пуничева Е.Л.",
    "Error": null
  },
  {
    "WeekDay": 2,
    "StartTime": "17:30",
    "Odd": 2,
    "Lesson": "Использование лесов для осуществления рекреационной деятельности",
    "LessonType": "л",
    "Room": "11-310",
    "FIO": "Пуничева Екатерина Леонидовна",
    "FIOshort": "Пуничева Е.Л.",
    "Error": null
  },
  {
    "WeekDay": 3,
    "StartTime": "14:00",
    "Odd": 1,
    "Lesson": "Заготовка древесины и других лесных ресурсов",
    "LessonType": "л",
    "Room": "3-903",
    "FIO": "Фрик Дмитрий Геннадьевич",
    "FIOshort": "Фрик Д.Г.",
    "Error": null
  },
  {
    "WeekDay": 3,
    "StartTime": "14:00",
    "Odd": 1,
    "Lesson": "Заготовка древесины и других лесных ресурсов",
    "LessonType": "л",
    "Room": "3-903",
    "FIO": "Фрик Дмитрий Геннадьевич",
    "FIOshort": "Фрик Д.Г.",
    "Error": null
  },
  {
    "WeekDay": 3,
    "StartTime": "14:00",
    "Odd": 2,
    "Lesson": "Заготовка древесины и других лесных ресурсов",
    "LessonType": "л",
    "Room": "5-411",
    "FIO": "Фрик Дмитрий Геннадьевич",
    "FIOshort": "Фрик Д.Г.",
    "Error": null
  },
  {
    "WeekDay": 3,
    "StartTime": "14:00",
    "Odd": 2,
    "Lesson": "Заготовка древесины и других лесных ресурсов",
    "LessonType": "л",
    "Room": "5-411",
    "FIO": "Фрик Дмитрий Геннадьевич",
    "FIOshort": "Фрик Д.Г.",
    "Error": null
  },
  {
    "WeekDay": 3,
    "StartTime": "15:45",
    "Odd": 0,
    "Lesson": "Контроль за состоянием и использованием лесных участков",
    "LessonType": "л",
    "Room": "5-404",
    "FIO": "Медведев Сергей Николаевич",
    "FIOshort": "Медведев С.Н.",
    "Error": null
  },
  {
    "WeekDay": 3,
    "StartTime": "15:45",
    "Odd": 0,
    "Lesson": "Контроль за состоянием и использованием лесных участков",
    "LessonType": "л",
    "Room": "5-404",
    "FIO": "Медведев Сергей Николаевич",
    "FIOshort": "Медведев С.Н.",
    "Error": null
  },
  {
    "WeekDay": 3,
    "StartTime": "17:30",
    "Odd": 0,
    "Lesson": "Контроль за состоянием и использованием лесных участков",
    "LessonType": "пр",
    "Room": "5-410",
    "FIO": "Медведев Сергей Николаевич",
    "FIOshort": "Медведев С.Н.",
    "Error": null
  },
  {
    "WeekDay": 3,
    "StartTime": "17:30",
    "Odd": 0,
    "Lesson": "Контроль за состоянием и использованием лесных участков",
    "LessonType": "пр",
    "Room": "5-410",
    "FIO": "Медведев Сергей Николаевич",
    "FIOshort": "Медведев С.Н.",
    "Error": null
  },
  {
    "WeekDay": 4,
    "StartTime": "10:15",
    "Odd": 0,
    "Lesson": "Физическая культура",
    "LessonType": "пр",
    "Room": "12-004",
    "FIO": "Афонина Светлана Владимировна",
    "FIOshort": "Афонина С.В.",
    "Error": null
  },
  {
    "WeekDay": 4,
    "StartTime": "10:15",
    "Odd": 0,
    "Lesson": "Физическая культура",
    "LessonType": "пр",
    "Room": "12-004",
    "FIO": "Афонина Светлана Владимировна",
    "FIOshort": "Афонина С.В.",
    "Error": null
  },
  {
    "WeekDay": 4,
    "StartTime": "12:00",
    "Odd": 0,
    "Lesson": "Использование лесов для осуществления рекреационной деятельности",
    "LessonType": "пр",
    "Room": "12-206",
    "FIO": "Пуничева Екатерина Леонидовна",
    "FIOshort": "Пуничева Е.Л.",
    "Error": null
  },
  {
    "WeekDay": 4,
    "StartTime": "12:00",
    "Odd": 0,
    "Lesson": "Использование лесов для осуществления рекреационной деятельности",
    "LessonType": "пр",
    "Room": "12-206",
    "FIO": "Пуничева Екатерина Леонидовна",
    "FIOshort": "Пуничева Е.Л.",
    "Error": null
  },
  {
    "WeekDay": 4,
    "StartTime": "14:00",
    "Odd": 1,
    "Lesson": "Контроль за состоянием и использованием лесных участков",
    "LessonType": "л",
    "Room": "12-203",
    "FIO": "Медведев Сергей Николаевич",
    "FIOshort": "Медведев С.Н.",
    "Error": null
  },
  {
    "WeekDay": 4,
    "StartTime": "14:00",
    "Odd": 1,
    "Lesson": "Контроль за состоянием и использованием лесных участков",
    "LessonType": "л",
    "Room": "12-203",
    "FIO": "Медведев Сергей Николаевич",
    "FIOshort": "Медведев С.Н.",
    "Error": null
  },
  {
    "WeekDay": 4,
    "StartTime": "14:00",
    "Odd": 2,
    "Lesson": "Контроль за состоянием и использованием лесных участков",
    "LessonType": "л",
    "Room": "12-001",
    "FIO": "Медведев Сергей Николаевич",
    "FIOshort": "Медведев С.Н.",
    "Error": null
  },
  {
    "WeekDay": 4,
    "StartTime": "14:00",
    "Odd": 2,
    "Lesson": "Контроль за состоянием и использованием лесных участков",
    "LessonType": "л",
    "Room": "12-001",
    "FIO": "Медведев Сергей Николаевич",
    "FIOshort": "Медведев С.Н.",
    "Error": null
  },
  {
    "WeekDay": 4,
    "StartTime": "15:45",
    "Odd": 0,
    "Lesson": "Контроль за состоянием и использованием лесных участков",
    "LessonType": "пр",
    "Room": "12-303",
    "FIO": "Медведев Сергей Николаевич",
    "FIOshort": "Медведев С.Н.",
    "Error": null
  },
  {
    "WeekDay": 4,
    "StartTime": "15:45",
    "Odd": 0,
    "Lesson": "Контроль за состоянием и использованием лесных участков",
    "LessonType": "пр",
    "Room": "12-303",
    "FIO": "Медведев Сергей Николаевич",
    "FIOshort": "Медведев С.Н.",
    "Error": null
  },
  {
    "WeekDay": 5,
    "StartTime": "12:00",
    "Odd": 1,
    "Lesson": "Использование лесов для осуществления рекреационной деятельности",
    "LessonType": "л",
    "Room": "11-403",
    "FIO": "Пуничева Екатерина Леонидовна",
    "FIOshort": "Пуничева Е.Л.",
    "Error": null
  },
  {
    "WeekDay": 5,
    "StartTime": "12:00",
    "Odd": 1,
    "Lesson": "Использование лесов для осуществления рекреационной деятельности",
    "LessonType": "л",
    "Room": "11-403",
    "FIO": "Пуничева Екатерина Леонидовна",
    "FIOshort": "Пуничева Е.Л.",
    "Error": null
  },
  {
    "WeekDay": 5,
    "StartTime": "14:00",
    "Odd": 1,
    "Lesson": "Заготовка древесины и других лесных ресурсов",
    "LessonType": "л",
    "Room": "11-415",
    "FIO": "Фрик Дмитрий Геннадьевич",
    "FIOshort": "Фрик Д.Г.",
    "Error": null
  },
  {
    "WeekDay": 5,
    "StartTime": "14:00",
    "Odd": 1,
    "Lesson": "Заготовка древесины и других лесных ресурсов",
    "LessonType": "пр",
    "Room": "11-415",
    "FIO": "Фрик Дмитрий Геннадьевич",
    "FIOshort": "Фрик Д.Г.",
    "Error": null
  },
  {
    "WeekDay": 5,
    "StartTime": "14:00",
    "Odd": 2,
    "Lesson": "Заготовка древесины и других лесных ресурсов",
    "LessonType": "л",
    "Room": "11-403",
    "FIO": "Фрик Дмитрий Геннадьевич",
    "FIOshort": "Фрик Д.Г.",
    "Error": null
  },
  {
    "WeekDay": 5,
    "StartTime": "14:00",
    "Odd": 2,
    "Lesson": "Заготовка древесины и других лесных ресурсов",
    "LessonType": "л",
    "Room": "11-403",
    "FIO": "Фрик Дмитрий Геннадьевич",
    "FIOshort": "Фрик Д.Г.",
    "Error": null
  },
  {
    "WeekDay": 5,
    "StartTime": "15:45",
    "Odd": 0,
    "Lesson": "Иностранный язык",
    "LessonType": "пр",
    "Room": "11-006",
    "FIO": "Кольцова Алла Викторовна",
    "FIOshort": "Кольцова А.В.",
    "Error": null
  },
  {
    "WeekDay": 5,
    "StartTime": "15:45",
    "Odd": 0,
    "Lesson": "Иностранный язык",
    "LessonType": "пр",
    "Room": "11-006",
    "FIO": "Кольцова Алла Викторовна",
    "FIOshort": "Кольцова А.В.",
    "Error": null
  },
  {
    "WeekDay": 5,
    "StartTime": "17:30",
    "Odd": 0,
    "Lesson": "Заготовка древесины и других лесных ресурсов",
    "LessonType": "пр",
    "Room": "11-309",
    "FIO": "Фрик Дмитрий Геннадьевич",
    "FIOshort": "Фрик Д.Г.",
    "Error": null
  },
  {
    "WeekDay": 5,
    "StartTime": "17:30",
    "Odd": 0,
    "Lesson": "Заготовка древесины и других лесных ресурсов",
    "LessonType": "пр",
    "Room": "11-309",
    "FIO": "Фрик Дмитрий Геннадьевич",
    "FIOshort": "Фрик Д.Г.",
    "Error": null
  },
  {
    "WeekDay": 6,
    "StartTime": "8:30",
    "Odd": 2,
    "Lesson": "Использование лесов для осуществления рекреационной деятельности",
    "LessonType": "л",
    "Room": "12-406",
    "FIO": "Пуничева Екатерина Леонидовна",
    "FIOshort": "Пуничева Е.Л.",
    "Error": null
  },
  {
    "WeekDay": 6,
    "StartTime": "8:30",
    "Odd": 2,
    "Lesson": "Использование лесов для осуществления рекреационной деятельности",
    "LessonType": "л",
    "Room": "12-406",
    "FIO": "Пуничева Екатерина Леонидовна",
    "FIOshort": "Пуничева Е.Л.",
    "Error": null
  },
  {
    "WeekDay": 6,
    "StartTime": "10:15",
    "Odd": 2,
    "Lesson": "Использование лесов для осуществления рекреационной деятельности",
    "LessonType": "л",
    "Room": "12-406",
    "FIO": "Пуничева Екатерина Леонидовна",
    "FIOshort": "Пуничева Е.Л.",
    "Error": null
  },
  {
    "WeekDay": 6,
    "StartTime": "10:15",
    "Odd": 2,
    "Lesson": "Использование лесов для осуществления рекреационной деятельности",
    "LessonType": "л",
    "Room": "12-406",
    "FIO": "Пуничева Екатерина Леонидовна",
    "FIOshort": "Пуничева Е.Л.",
    "Error": null
  },
  {
    "WeekDay": 6,
    "StartTime": "14:00",
    "Odd": 1,
    "Lesson": "Заготовка древесины и других лесных ресурсов",
    "LessonType": "л",
    "Room": "12-406",
    "FIO": "Фрик Дмитрий Геннадьевич",
    "FIOshort": "Фрик Д.Г.",
    "Error": null
  },
  {
    "WeekDay": 6,
    "StartTime": "14:00",
    "Odd": 1,
    "Lesson": "Заготовка древесины и других лесных ресурсов",
    "LessonType": "л",
    "Room": "12-406",
    "FIO": "Фрик Дмитрий Геннадьевич",
    "FIOshort": "Фрик Д.Г.",
    "Error": null
  },
  {
    "WeekDay": 6,
    "StartTime": "15:45",
    "Odd": 1,
    "Lesson": "Основы философии",
    "LessonType": "пр",
    "Room": "12-406",
    "FIO": "Тараканов Павел Николаевич",
    "FIOshort": "Тараканов П.Н.",
    "Error": null
  },
  {
    "WeekDay": 6,
    "StartTime": "15:45",
    "Odd": 1,
    "Lesson": "Основы философии",
    "LessonType": "л",
    "Room": "12-406",
    "FIO": "Тараканов Павел Николаевич",
    "FIOshort": "Тараканов П.Н.",
    "Error": null
  }
]
