[
  {
    "WeekDay": 1,
    "StartTime": "8:30",
    "Odd": 0,
    "Lesson": "Туристские ресурсы Байкальского региона",
    "LessonType": "л",
    "Room": "11-205",
    "FIO": "Молоцило Джамиля Яралиевна",
    "FIOshort": "Молоцило Д.Я.",
    "Error": null
  },
  {
    "WeekDay": 1,
    "StartTime": "10:15",
    "Odd": 0,
    "Lesson": "Маркетинговые технологии в туризме",
    "LessonType": "л",
    "Room": "11-205",
    "FIO": "Старухина Нина Эдуардовна",
    "FIOshort": "Старухина Н.Э.",
    "Error": null
  },
  {
    "WeekDay": 1,
    "StartTime": "12:00",
    "Odd": 0,
    "Lesson": "Иностранный язык",
    "LessonType": "пр",
    "Room": "11-415",
    "FIO": "Ефимцева Ирина Андреевна",
    "FIOshort": "Ефимцева И.А.",
    "Error": null
  },
  {
    "WeekDay": 1,
    "StartTime": "14:00",
    "Odd": 0,
    "Lesson": "Маркетинговые технологии в туризме",
    "LessonType": "пр",
    "Room": "11-301",
    "FIO": "Старухина Нина Эдуардовна",
    "FIOshort": "Старухина Н.Э.",
    "Error": null
  },
  {
    "WeekDay": 2,
    "StartTime": "14:00",
    "Odd": 0,
    "Lesson": "Безопасность жизнедеятельности",
    "LessonType": "л",
    "Room": "12-101",
    "FIO": "Тюрюханова Татьяна Леонидовна",
    "FIOshort": "Тюрюханова Т.Л.",
    "Error": null
  },
  {
    "WeekDay": 2,
    "StartTime": "15:45",
    "Odd": 0,
    "Lesson": "Экономика туризма",
    "LessonType": "л",
    "Room": "12-101",
    "FIO": "Петров Николай Витальевич",
    "FIOshort": "Петров Н.В.",
    "Error": null
  },
  {
    "WeekDay": 3,
    "StartTime": "12:00",
    "Odd": 1,
    "Lesson": "Безопасность жизнедеятельности",
    "LessonType": "л",
    "Room": "12-101",
    "FIO": "Тюрюханова Татьяна Леонидовна",
    "FIOshort": "Тюрюханова Т.Л.",
    "Error": null
  },
  {
    "WeekDay": 3,
    "StartTime": "12:00",
    "Odd": 2,
    "Lesson": "Экскурсоведение",
    "LessonType": "л",
    "Room": "12-409",
    "FIO": "Кузнецова Елена Владимировна",
    "FIOshort": "Кузнецова Е.В.",
    "Error": null
  },
  {
    "WeekDay": 3,
    "StartTime": "14:00",
    "Odd": 0,
    "Lesson": "Математика",
    "LessonType": "л",
    "Room": "12-407",
    "FIO": "Лапаева Татьяна Николаевна",
    "FIOshort": "Лапаева Т.Н.",
    "Error": null
  },
  {
    "WeekDay": 4,
    "StartTime": "10:15",
    "Odd": 0,
    "Lesson": "Туристские ресурсы Байкальского региона",
    "LessonType": "пр",
    "Room": "11-304",
    "FIO": "Молоцило Джамиля Яралиевна",
    "FIOshort": "Молоцило Д.Я.",
    "Error": null
  },
  {
    "WeekDay": 4,
    "StartTime": "12:00",
    "Odd": 0,
    "Lesson": "Технология и организация туроператорской деятельности",
    "LessonType": "л",
    "Room": "11-205",
    "FIO": "Казачкова Ольга Павловна",
    "FIOshort": "Казачкова О.П.",
    "Error": null
  },
  {
    "WeekDay": 4,
    "StartTime": "14:00",
    "Odd": 0,
    "Lesson": "Технология и организация туроператорской деятельности",
    "LessonType": "пр",
    "Room": "11-302",
    "FIO": "Казачкова Ольга Павловна",
    "FIOshort": "Казачкова О.П.",
    "Error": null
  },
  {
    "WeekDay": 4,
    "StartTime": "15:45",
    "Odd": 0,
    "Lesson": "Физическая культура",
    "LessonType": "пр",
    "Room": "11-103",
    "FIO": "Афонина Светлана Владимировна",
    "FIOshort": "Афонина С.В.",
    "Error": null
  },
  {
    "WeekDay": 5,
    "StartTime": "10:15",
    "Odd": 1,
    "Lesson": "Экскурсоведение",
    "LessonType": "пр",
    "Room": "12-305",
    "FIO": "Кузнецова Елена Владимировна",
    "FIOshort": "Кузнецова Е.В.",
    "Error": null
  },
  {
    "WeekDay": 5,
    "StartTime": "12:00",
    "Odd": 1,
    "Lesson": "Безопасность жизнедеятельности",
    "LessonType": "пр",
    "Room": "12-101",
    "FIO": "Тюрюханова Татьяна Леонидовна",
    "FIOshort": "Тюрюханова Т.Л.",
    "Error": null
  },
  {
    "WeekDay": 5,
    "StartTime": "12:00",
    "Odd": 2,
    "Lesson": "Математика",
    "LessonType": "пр",
    "Room": "12-406",
    "FIO": "Лапаева Татьяна Николаевна",
    "FIOshort": "Лапаева Т.Н.",
    "Error": null
  },
  {
    "WeekDay": 5,
    "StartTime": "14:00",
    "Odd": 0,
    "Lesson": "Иностранный язык",
    "LessonType": "пр",
    "Room": "12-305",
    "FIO": "Ефимцева Ирина Андреевна",
    "FIOshort": "Ефимцева И.А.",
    "Error": null
  },
  {
    "WeekDay": 5,
    "StartTime": "15:45",
    "Odd": 2,
    "Lesson": "Экскурсоведение",
    "LessonType": "л",
    "Room": "12-101",
    "FIO": "Кузнецова Елена Владимировна",
    "FIOshort": "Кузнецова Е.В.",
    "Error": null
  },
  {
    "WeekDay": 6,
    "StartTime": "10:15",
    "Odd": 0,
    "Lesson": "Технология и организация туроператорской деятельности",
    "LessonType": "л",
    "Room": "11-205",
    "FIO": "Казачкова Ольга Павловна",
    "FIOshort": "Казачкова О.П.",
    "Error": null
  },
  {
    "WeekDay": 6,
    "StartTime": "12:00",
    "Odd": 0,
    "Lesson": "Технология и организация туроператорской деятельности",
    "LessonType": "пр",
    "Room": "11-112",
    "FIO": "Казачкова Ольга Павловна",
    "FIOshort": "Казачкова О.П.",
    "Error": null
  },
  {
    "WeekDay": 6,
    "StartTime": "14:00",
    "Odd": 0,
    "Lesson": "Экономика туризма",
    "LessonType": "пр",
    "Room": "11-306",
    "FIO": "Петров Николай Витальевич",
    "FIOshort": "Петров Н.В.",
    "Error": null
  }
]
